{".class": "MypyFile", "_fullname": "abjad.core.Leaf", "is_partial_stub_package": false, "is_stub": false, "names": {".class": "SymbolTable", "Component": {".class": "SymbolTableNode", "cross_ref": "abjad.core.Component.Component", "kind": "Gdef"}, "Duration": {".class": "SymbolTableNode", "cross_ref": "abjad.utilities.Duration.Duration", "kind": "Gdef"}, "FormatSpecification": {".class": "SymbolTableNode", "cross_ref": "abjad.system.FormatSpecification.FormatSpecification", "kind": "Gdef"}, "Leaf": {".class": "SymbolTableNode", "kind": "Gdef", "node": {".class": "TypeInfo", "_promote": null, "abstract_attributes": ["__init__"], "bases": ["abjad.core.Component.Component"], "declared_metaclass": null, "defn": {".class": "ClassDef", "fullname": "abjad.core.Leaf.Leaf", "name": "Leaf", "type_vars": []}, "flags": ["is_abstract"], "fullname": "abjad.core.Leaf.Leaf", "metaclass_type": null, "metadata": {}, "module_name": "abjad.core.Leaf", "mro": ["abjad.core.Leaf.Leaf", "abjad.core.Component.Component", "builtins.object"], "names": {".class": "SymbolTable", "__copy__": {".class": "SymbolTableNode", "kind": "Mdef", "node": {".class": "FuncDef", "arg_kinds": [0, 2], "arg_names": ["self", "arguments"], "flags": [], "fullname": "abjad.core.Leaf.Leaf.__copy__", "name": "__copy__", "type": null}}, "__getnewargs__": {".class": "SymbolTableNode", "kind": "Mdef", "node": {".class": "FuncDef", "arg_kinds": [0], "arg_names": ["self"], "flags": [], "fullname": "abjad.core.Leaf.Leaf.__getnewargs__", "name": "__getnewargs__", "type": null}}, "__init__": {".class": "SymbolTableNode", "kind": "Mdef", "node": {".class": "Decorator", "func": {".class": "FuncDef", "arg_kinds": [0, 0, 5, 5], "arg_names": ["self", "written_duration", "multiplier", "tag"], "flags": ["is_decorated", "is_abstract"], "fullname": "abjad.core.Leaf.Leaf.__init__", "name": "__init__", "type": {".class": "CallableType", "arg_kinds": [0, 0, 5, 5], "arg_names": ["self", "written_duration", "multiplier", "tag"], "arg_types": ["abjad.core.Leaf.Leaf", {".class": "AnyType", "missing_import_name": null, "source_any": null, "type_of_any": 1}, {".class": "AnyType", "missing_import_name": null, "source_any": null, "type_of_any": 1}, {".class": "UnionType", "items": ["abjad.system.Tag.Tag", {".class": "NoneType"}]}], "bound_args": [], "def_extras": {"first_arg": "self"}, "fallback": "builtins.function", "implicit": false, "is_ellipsis_args": false, "name": "__init__ of Leaf", "ret_type": {".class": "NoneType"}, "variables": []}}, "is_overload": false, "var": {".class": "Var", "flags": ["is_initialized_in_class", "is_ready"], "fullname": null, "name": "__init__", "type": {".class": "CallableType", "arg_kinds": [0, 0, 5, 5], "arg_names": ["self", "written_duration", "multiplier", "tag"], "arg_types": ["abjad.core.Leaf.Leaf", {".class": "AnyType", "missing_import_name": null, "source_any": null, "type_of_any": 1}, {".class": "AnyType", "missing_import_name": null, "source_any": null, "type_of_any": 1}, {".class": "UnionType", "items": ["abjad.system.Tag.Tag", {".class": "NoneType"}]}], "bound_args": [], "def_extras": {"first_arg": "self"}, "fallback": "builtins.function", "implicit": false, "is_ellipsis_args": false, "name": "__init__ of Leaf", "ret_type": {".class": "NoneType"}, "variables": []}}}}, "__slots__": {".class": "SymbolTableNode", "kind": "Mdef", "node": {".class": "Var", "flags": ["is_initialized_in_class"], "fullname": "abjad.core.Leaf.Leaf.__slots__", "name": "__slots__", "type": {".class": "TupleType", "implicit": false, "items": ["builtins.str", "builtins.str", "builtins.str", "builtins.str"], "partial_fallback": {".class": "Instance", "args": [{".class": "AnyType", "missing_import_name": null, "source_any": null, "type_of_any": 6}], "type_ref": "builtins.tuple"}}}}, "__str__": {".class": "SymbolTableNode", "kind": "Mdef", "node": {".class": "FuncDef", "arg_kinds": [0], "arg_names": ["self"], "flags": [], "fullname": "abjad.core.Leaf.Leaf.__str__", "name": "__str__", "type": {".class": "CallableType", "arg_kinds": [0], "arg_names": [null], "arg_types": ["abjad.core.Leaf.Leaf"], "bound_args": [], "def_extras": {"first_arg": "self"}, "fallback": "builtins.function", "implicit": false, "is_ellipsis_args": false, "name": "__str__ of Leaf", "ret_type": "builtins.str", "variables": []}}}, "_after_grace_container": {".class": "SymbolTableNode", "implicit": true, "kind": "Mdef", "node": {".class": "Var", "flags": [], "fullname": "abjad.core.Leaf.Leaf._after_grace_container", "name": "_after_grace_container", "type": {".class": "NoneType"}}}, "_allowable_format_slots": {".class": "SymbolTableNode", "kind": "Mdef", "node": {".class": "Var", "flags": ["is_initialized_in_class"], "fullname": "abjad.core.Leaf.Leaf._allowable_format_slots", "name": "_allowable_format_slots", "type": {".class": "TupleType", "implicit": false, "items": ["builtins.str", "builtins.str", "builtins.str", "builtins.str"], "partial_fallback": {".class": "Instance", "args": [{".class": "AnyType", "missing_import_name": null, "source_any": null, "type_of_any": 6}], "type_ref": "builtins.tuple"}}}}, "_as_graphviz_node": {".class": "SymbolTableNode", "kind": "Mdef", "node": {".class": "FuncDef", "arg_kinds": [0], "arg_names": ["self"], "flags": [], "fullname": "abjad.core.Leaf.Leaf._as_graphviz_node", "name": "_as_graphviz_node", "type": null}}, "_before_grace_container": {".class": "SymbolTableNode", "implicit": true, "kind": "Mdef", "node": {".class": "Var", "flags": [], "fullname": "abjad.core.Leaf.Leaf._before_grace_container", "name": "_before_grace_container", "type": {".class": "NoneType"}}}, "_copy_override_and_set_from_leaf": {".class": "SymbolTableNode", "kind": "Mdef", "node": {".class": "FuncDef", "arg_kinds": [0, 0], "arg_names": ["self", "leaf"], "flags": [], "fullname": "abjad.core.Leaf.Leaf._copy_override_and_set_from_leaf", "name": "_copy_override_and_set_from_leaf", "type": null}}, "_format_after_grace_body": {".class": "SymbolTableNode", "kind": "Mdef", "node": {".class": "FuncDef", "arg_kinds": [0], "arg_names": ["self"], "flags": [], "fullname": "abjad.core.Leaf.Leaf._format_after_grace_body", "name": "_format_after_grace_body", "type": null}}, "_format_after_grace_command": {".class": "SymbolTableNode", "kind": "Mdef", "node": {".class": "FuncDef", "arg_kinds": [0], "arg_names": ["self"], "flags": [], "fullname": "abjad.core.Leaf.Leaf._format_after_grace_command", "name": "_format_after_grace_command", "type": null}}, "_format_after_slot": {".class": "SymbolTableNode", "kind": "Mdef", "node": {".class": "FuncDef", "arg_kinds": [0, 0], "arg_names": ["self", "bundle"], "flags": [], "fullname": "abjad.core.Leaf.Leaf._format_after_slot", "name": "_format_after_slot", "type": null}}, "_format_before_slot": {".class": "SymbolTableNode", "kind": "Mdef", "node": {".class": "FuncDef", "arg_kinds": [0, 0], "arg_names": ["self", "bundle"], "flags": [], "fullname": "abjad.core.Leaf.Leaf._format_before_slot", "name": "_format_before_slot", "type": null}}, "_format_closing_slot": {".class": "SymbolTableNode", "kind": "Mdef", "node": {".class": "FuncDef", "arg_kinds": [0, 0], "arg_names": ["self", "bundle"], "flags": [], "fullname": "abjad.core.Leaf.Leaf._format_closing_slot", "name": "_format_closing_slot", "type": null}}, "_format_contents_slot": {".class": "SymbolTableNode", "kind": "Mdef", "node": {".class": "FuncDef", "arg_kinds": [0, 0], "arg_names": ["self", "bundle"], "flags": [], "fullname": "abjad.core.Leaf.Leaf._format_contents_slot", "name": "_format_contents_slot", "type": null}}, "_format_grace_body": {".class": "SymbolTableNode", "kind": "Mdef", "node": {".class": "FuncDef", "arg_kinds": [0], "arg_names": ["self"], "flags": [], "fullname": "abjad.core.Leaf.Leaf._format_grace_body", "name": "_format_grace_body", "type": null}}, "_format_leaf_body": {".class": "SymbolTableNode", "kind": "Mdef", "node": {".class": "FuncDef", "arg_kinds": [0, 0], "arg_names": ["self", "bundle"], "flags": [], "fullname": "abjad.core.Leaf.Leaf._format_leaf_body", "name": "_format_leaf_body", "type": null}}, "_format_leaf_nucleus": {".class": "SymbolTableNode", "kind": "Mdef", "node": {".class": "FuncDef", "arg_kinds": [0], "arg_names": ["self"], "flags": [], "fullname": "abjad.core.Leaf.Leaf._format_leaf_nucleus", "name": "_format_leaf_nucleus", "type": null}}, "_format_opening_slot": {".class": "SymbolTableNode", "kind": "Mdef", "node": {".class": "FuncDef", "arg_kinds": [0, 0], "arg_names": ["self", "bundle"], "flags": [], "fullname": "abjad.core.Leaf.Leaf._format_opening_slot", "name": "_format_opening_slot", "type": null}}, "_get_compact_representation": {".class": "SymbolTableNode", "kind": "Mdef", "node": {".class": "FuncDef", "arg_kinds": [0], "arg_names": ["self"], "flags": [], "fullname": "abjad.core.Leaf.Leaf._get_compact_representation", "name": "_get_compact_representation", "type": null}}, "_get_duration_in_seconds": {".class": "SymbolTableNode", "kind": "Mdef", "node": {".class": "FuncDef", "arg_kinds": [0], "arg_names": ["self"], "flags": [], "fullname": "abjad.core.Leaf.Leaf._get_duration_in_seconds", "name": "_get_duration_in_seconds", "type": null}}, "_get_format_pieces": {".class": "SymbolTableNode", "kind": "Mdef", "node": {".class": "FuncDef", "arg_kinds": [0], "arg_names": ["self"], "flags": [], "fullname": "abjad.core.Leaf.Leaf._get_format_pieces", "name": "_get_format_pieces", "type": null}}, "_get_format_specification": {".class": "SymbolTableNode", "kind": "Mdef", "node": {".class": "FuncDef", "arg_kinds": [0], "arg_names": ["self"], "flags": [], "fullname": "abjad.core.Leaf.Leaf._get_format_specification", "name": "_get_format_specification", "type": null}}, "_get_formatted_duration": {".class": "SymbolTableNode", "kind": "Mdef", "node": {".class": "FuncDef", "arg_kinds": [0], "arg_names": ["self"], "flags": [], "fullname": "abjad.core.Leaf.Leaf._get_formatted_duration", "name": "_get_formatted_duration", "type": null}}, "_get_logical_tie": {".class": "SymbolTableNode", "kind": "Mdef", "node": {".class": "FuncDef", "arg_kinds": [0], "arg_names": ["self"], "flags": [], "fullname": "abjad.core.Leaf.Leaf._get_logical_tie", "name": "_get_logical_tie", "type": null}}, "_get_multiplied_duration": {".class": "SymbolTableNode", "kind": "Mdef", "node": {".class": "FuncDef", "arg_kinds": [0], "arg_names": ["self"], "flags": [], "fullname": "abjad.core.Leaf.Leaf._get_multiplied_duration", "name": "_get_multiplied_duration", "type": null}}, "_get_preprolated_duration": {".class": "SymbolTableNode", "kind": "Mdef", "node": {".class": "FuncDef", "arg_kinds": [0], "arg_names": ["self"], "flags": [], "fullname": "abjad.core.Leaf.Leaf._get_preprolated_duration", "name": "_get_preprolated_duration", "type": null}}, "_leaf": {".class": "SymbolTableNode", "kind": "Mdef", "node": {".class": "FuncDef", "arg_kinds": [0, 0], "arg_names": ["self", "n"], "flags": [], "fullname": "abjad.core.Leaf.Leaf._leaf", "name": "_leaf", "type": null}}, "_lilypond_setting_name_manager": {".class": "SymbolTableNode", "implicit": true, "kind": "Mdef", "node": {".class": "Var", "flags": [], "fullname": "abjad.core.Leaf.Leaf._lilypond_setting_name_manager", "name": "_lilypond_setting_name_manager", "type": {".class": "AnyType", "missing_import_name": null, "source_any": null, "type_of_any": 1}}}, "_multiplier": {".class": "SymbolTableNode", "implicit": true, "kind": "Mdef", "node": {".class": "Var", "flags": [], "fullname": "abjad.core.Leaf.Leaf._multiplier", "name": "_multiplier", "type": {".class": "AnyType", "missing_import_name": null, "source_any": null, "type_of_any": 1}}}, "_overrides": {".class": "SymbolTableNode", "implicit": true, "kind": "Mdef", "node": {".class": "Var", "flags": [], "fullname": "abjad.core.Leaf.Leaf._overrides", "name": "_overrides", "type": {".class": "AnyType", "missing_import_name": null, "source_any": null, "type_of_any": 1}}}, "_process_contribution_packet": {".class": "SymbolTableNode", "kind": "Mdef", "node": {".class": "FuncDef", "arg_kinds": [0, 0], "arg_names": ["self", "contribution_packet"], "flags": [], "fullname": "abjad.core.Leaf.Leaf._process_contribution_packet", "name": "_process_contribution_packet", "type": null}}, "_report_format_contributions": {".class": "SymbolTableNode", "kind": "Mdef", "node": {".class": "FuncDef", "arg_kinds": [0], "arg_names": ["self"], "flags": [], "fullname": "abjad.core.Leaf.Leaf._report_format_contributions", "name": "_report_format_contributions", "type": null}}, "_scale": {".class": "SymbolTableNode", "kind": "Mdef", "node": {".class": "FuncDef", "arg_kinds": [0, 0], "arg_names": ["self", "multiplier"], "flags": [], "fullname": "abjad.core.Leaf.Leaf._scale", "name": "_scale", "type": null}}, "_set_duration": {".class": "SymbolTableNode", "kind": "Mdef", "node": {".class": "FuncDef", "arg_kinds": [0, 0], "arg_names": ["self", "new_duration"], "flags": [], "fullname": "abjad.core.Leaf.Leaf._set_duration", "name": "_set_duration", "type": null}}, "_split_by_durations": {".class": "SymbolTableNode", "kind": "Mdef", "node": {".class": "FuncDef", "arg_kinds": [0, 0, 1], "arg_names": ["self", "durations", "cyclic"], "flags": [], "fullname": "abjad.core.Leaf.Leaf._split_by_durations", "name": "_split_by_durations", "type": null}}, "_written_duration": {".class": "SymbolTableNode", "implicit": true, "kind": "Mdef", "node": {".class": "Var", "flags": [], "fullname": "abjad.core.Leaf.Leaf._written_duration", "name": "_written_duration", "type": {".class": "AnyType", "missing_import_name": null, "source_any": null, "type_of_any": 1}}}, "multiplier": {".class": "SymbolTableNode", "kind": "Mdef", "node": {".class": "OverloadedFuncDef", "flags": ["is_property"], "fullname": "abjad.core.Leaf.Leaf.multiplier", "impl": null, "items": [{".class": "Decorator", "func": {".class": "FuncDef", "arg_kinds": [0], "arg_names": ["self"], "flags": ["is_property", "is_overload", "is_decorated"], "fullname": "abjad.core.Leaf.Leaf.multiplier", "name": "multiplier", "type": {".class": "CallableType", "arg_kinds": [0], "arg_names": ["self"], "arg_types": ["abjad.core.Leaf.Leaf"], "bound_args": [], "def_extras": {"first_arg": "self"}, "fallback": "builtins.function", "implicit": false, "is_ellipsis_args": false, "name": "multiplier of Leaf", "ret_type": {".class": "UnionType", "items": ["abjad.utilities.Multiplier.Multiplier", "abjad.mathtools.NonreducedFraction", {".class": "NoneType"}]}, "variables": []}}, "is_overload": true, "var": {".class": "Var", "flags": ["is_initialized_in_class", "is_property", "is_settable_property", "is_ready"], "fullname": null, "name": "multiplier", "type": {".class": "CallableType", "arg_kinds": [0], "arg_names": ["self"], "arg_types": ["abjad.core.Leaf.Leaf"], "bound_args": [], "def_extras": {"first_arg": "self"}, "fallback": "builtins.function", "implicit": false, "is_ellipsis_args": false, "name": "multiplier of Leaf", "ret_type": {".class": "UnionType", "items": ["abjad.utilities.Multiplier.Multiplier", "abjad.mathtools.NonreducedFraction", {".class": "NoneType"}]}, "variables": []}}}, {".class": "Decorator", "func": {".class": "FuncDef", "arg_kinds": [0, 0], "arg_names": ["self", "argument"], "flags": ["is_decorated"], "fullname": "abjad.core.Leaf.Leaf.multiplier", "name": "multiplier", "type": null}, "is_overload": false, "var": {".class": "Var", "flags": [], "fullname": null, "name": "multiplier", "type": null}}], "type": {".class": "Overloaded", "items": [{".class": "CallableType", "arg_kinds": [0], "arg_names": ["self"], "arg_types": ["abjad.core.Leaf.Leaf"], "bound_args": [], "def_extras": {"first_arg": "self"}, "fallback": "builtins.function", "implicit": false, "is_ellipsis_args": false, "name": "multiplier of Leaf", "ret_type": {".class": "UnionType", "items": ["abjad.utilities.Multiplier.Multiplier", "abjad.mathtools.NonreducedFraction", {".class": "NoneType"}]}, "variables": []}]}}}, "written_duration": {".class": "SymbolTableNode", "kind": "Mdef", "node": {".class": "OverloadedFuncDef", "flags": ["is_property"], "fullname": "abjad.core.Leaf.Leaf.written_duration", "impl": null, "items": [{".class": "Decorator", "func": {".class": "FuncDef", "arg_kinds": [0], "arg_names": ["self"], "flags": ["is_property", "is_overload", "is_decorated"], "fullname": "abjad.core.Leaf.Leaf.written_duration", "name": "written_duration", "type": {".class": "CallableType", "arg_kinds": [0], "arg_names": ["self"], "arg_types": ["abjad.core.Leaf.Leaf"], "bound_args": [], "def_extras": {"first_arg": "self"}, "fallback": "builtins.function", "implicit": false, "is_ellipsis_args": false, "name": "written_duration of Leaf", "ret_type": "abjad.utilities.Duration.Duration", "variables": []}}, "is_overload": true, "var": {".class": "Var", "flags": ["is_initialized_in_class", "is_property", "is_settable_property", "is_ready"], "fullname": null, "name": "written_duration", "type": {".class": "CallableType", "arg_kinds": [0], "arg_names": ["self"], "arg_types": ["abjad.core.Leaf.Leaf"], "bound_args": [], "def_extras": {"first_arg": "self"}, "fallback": "builtins.function", "implicit": false, "is_ellipsis_args": false, "name": "written_duration of Leaf", "ret_type": "abjad.utilities.Duration.Duration", "variables": []}}}, {".class": "Decorator", "func": {".class": "FuncDef", "arg_kinds": [0, 0], "arg_names": ["self", "argument"], "flags": ["is_decorated"], "fullname": "abjad.core.Leaf.Leaf.written_duration", "name": "written_duration", "type": null}, "is_overload": false, "var": {".class": "Var", "flags": [], "fullname": null, "name": "written_duration", "type": null}}], "type": {".class": "Overloaded", "items": [{".class": "CallableType", "arg_kinds": [0], "arg_names": ["self"], "arg_types": ["abjad.core.Leaf.Leaf"], "bound_args": [], "def_extras": {"first_arg": "self"}, "fallback": "builtins.function", "implicit": false, "is_ellipsis_args": false, "name": "written_duration of Leaf", "ret_type": "abjad.utilities.Duration.Duration", "variables": []}]}}}}, "tuple_type": null, "type_vars": [], "typeddict_type": null}}, "LilyPondFormatManager": {".class": "SymbolTableNode", "cross_ref": "abjad.system.LilyPondFormatManager.LilyPondFormatManager", "kind": "Gdef"}, "MetronomeMark": {".class": "SymbolTableNode", "cross_ref": "abjad.indicators.MetronomeMark.MetronomeMark", "kind": "Gdef"}, "Multiplier": {".class": "SymbolTableNode", "cross_ref": "abjad.utilities.Multiplier.Multiplier", "kind": "Gdef"}, "RepeatTie": {".class": "SymbolTableNode", "cross_ref": "abjad.indicators.RepeatTie.RepeatTie", "kind": "Gdef"}, "Sequence": {".class": "SymbolTableNode", "cross_ref": "abjad.utilities.Sequence.Sequence", "kind": "Gdef"}, "Tag": {".class": "SymbolTableNode", "cross_ref": "abjad.system.Tag.Tag", "kind": "Gdef"}, "Tie": {".class": "SymbolTableNode", "cross_ref": "abjad.indicators.Tie.Tie", "kind": "Gdef"}, "__doc__": {".class": "SymbolTableNode", "kind": "Gdef", "node": {".class": "Var", "flags": ["is_ready"], "fullname": "abjad.core.Leaf.__doc__", "name": "__doc__", "type": "builtins.str"}}, "__file__": {".class": "SymbolTableNode", "kind": "Gdef", "node": {".class": "Var", "flags": ["is_ready"], "fullname": "abjad.core.Leaf.__file__", "name": "__file__", "type": "builtins.str"}}, "__name__": {".class": "SymbolTableNode", "kind": "Gdef", "node": {".class": "Var", "flags": ["is_ready"], "fullname": "abjad.core.Leaf.__name__", "name": "__name__", "type": "builtins.str"}}, "__package__": {".class": "SymbolTableNode", "kind": "Gdef", "node": {".class": "Var", "flags": ["is_ready"], "fullname": "abjad.core.Leaf.__package__", "name": "__package__", "type": "builtins.str"}}, "abc": {".class": "SymbolTableNode", "cross_ref": "abc", "kind": "Gdef"}, "attach": {".class": "SymbolTableNode", "cross_ref": "abjad.top.attach.attach", "kind": "Gdef"}, "copy": {".class": "SymbolTableNode", "cross_ref": "copy", "kind": "Gdef"}, "detach": {".class": "SymbolTableNode", "cross_ref": "abjad.top.detach.detach", "kind": "Gdef"}, "enums": {".class": "SymbolTableNode", "cross_ref": "abjad.enums", "kind": "Gdef"}, "exceptions": {".class": "SymbolTableNode", "cross_ref": "abjad.exceptions", "kind": "Gdef"}, "inspect": {".class": "SymbolTableNode", "cross_ref": "abjad.top.inspect.inspect", "kind": "Gdef"}, "mathtools": {".class": "SymbolTableNode", "cross_ref": "abjad.mathtools", "kind": "Gdef"}, "mutate": {".class": "SymbolTableNode", "cross_ref": "abjad.top.mutate.mutate", "kind": "Gdef"}, "override": {".class": "SymbolTableNode", "cross_ref": "abjad.top.override.override", "kind": "Gdef"}, "select": {".class": "SymbolTableNode", "cross_ref": "abjad.top.select.select", "kind": "Gdef"}, "setting": {".class": "SymbolTableNode", "cross_ref": "abjad.top.setting.setting", "kind": "Gdef"}, "typing": {".class": "SymbolTableNode", "cross_ref": "typing", "kind": "Gdef"}, "uqbar": {".class": "SymbolTableNode", "kind": "Gdef", "node": {".class": "Var", "flags": ["is_suppressed_import", "is_ready"], "fullname": "abjad.core.Leaf.uqbar", "name": "uqbar", "type": {".class": "AnyType", "missing_import_name": "abjad.core.Leaf.uqbar", "source_any": null, "type_of_any": 3}}}}, "path": "/Users/evansdsg2/abjad/abjad/core/Leaf.py"}