{".class": "MypyFile", "_fullname": "abjad.pitch.Accidental", "is_partial_stub_package": false, "is_stub": false, "names": {".class": "SymbolTable", "Accidental": {".class": "SymbolTableNode", "kind": "Gdef", "node": {".class": "TypeInfo", "_promote": null, "abstract_attributes": [], "bases": ["builtins.object"], "declared_metaclass": null, "defn": {".class": "ClassDef", "fullname": "abjad.pitch.Accidental.Accidental", "name": "Accidental", "type_vars": []}, "flags": [], "fullname": "abjad.pitch.Accidental.Accidental", "metaclass_type": null, "metadata": {}, "module_name": "abjad.pitch.Accidental", "mro": ["abjad.pitch.Accidental.Accidental", "builtins.object"], "names": {".class": "SymbolTable", "__add__": {".class": "SymbolTableNode", "kind": "Mdef", "node": {".class": "FuncDef", "arg_kinds": [0, 0], "arg_names": ["self", "argument"], "flags": [], "fullname": "abjad.pitch.Accidental.Accidental.__add__", "name": "__add__", "type": null}}, "__call__": {".class": "SymbolTableNode", "kind": "Mdef", "node": {".class": "FuncDef", "arg_kinds": [0, 0], "arg_names": ["self", "argument"], "flags": [], "fullname": "abjad.pitch.Accidental.Accidental.__call__", "name": "__call__", "type": null}}, "__eq__": {".class": "SymbolTableNode", "kind": "Mdef", "node": {".class": "FuncDef", "arg_kinds": [0, 0], "arg_names": ["self", "argument"], "flags": [], "fullname": "abjad.pitch.Accidental.Accidental.__eq__", "name": "__eq__", "type": {".class": "CallableType", "arg_kinds": [0, 0], "arg_names": [null, null], "arg_types": ["abjad.pitch.Accidental.Accidental", {".class": "AnyType", "missing_import_name": null, "source_any": null, "type_of_any": 1}], "bound_args": [], "def_extras": {"first_arg": "self"}, "fallback": "builtins.function", "implicit": false, "is_ellipsis_args": false, "name": "__eq__ of Accidental", "ret_type": "builtins.bool", "variables": []}}}, "__hash__": {".class": "SymbolTableNode", "kind": "Mdef", "node": {".class": "FuncDef", "arg_kinds": [0], "arg_names": ["self"], "flags": [], "fullname": "abjad.pitch.Accidental.Accidental.__hash__", "name": "__hash__", "type": {".class": "CallableType", "arg_kinds": [0], "arg_names": ["self"], "arg_types": ["abjad.pitch.Accidental.Accidental"], "bound_args": [], "def_extras": {"first_arg": "self"}, "fallback": "builtins.function", "implicit": false, "is_ellipsis_args": false, "name": "__hash__ of Accidental", "ret_type": "builtins.int", "variables": []}}}, "__init__": {".class": "SymbolTableNode", "kind": "Mdef", "node": {".class": "FuncDef", "arg_kinds": [0, 1, 5], "arg_names": ["self", "name", "arrow"], "flags": [], "fullname": "abjad.pitch.Accidental.Accidental.__init__", "name": "__init__", "type": null}}, "__lt__": {".class": "SymbolTableNode", "kind": "Mdef", "node": {".class": "FuncDef", "arg_kinds": [0, 0], "arg_names": ["self", "argument"], "flags": [], "fullname": "abjad.pitch.Accidental.Accidental.__lt__", "name": "__lt__", "type": null}}, "__neg__": {".class": "SymbolTableNode", "kind": "Mdef", "node": {".class": "FuncDef", "arg_kinds": [0], "arg_names": ["self"], "flags": [], "fullname": "abjad.pitch.Accidental.Accidental.__neg__", "name": "__neg__", "type": null}}, "__radd__": {".class": "SymbolTableNode", "kind": "Mdef", "node": {".class": "FuncDef", "arg_kinds": [0, 0], "arg_names": ["self", "argument"], "flags": [], "fullname": "abjad.pitch.Accidental.Accidental.__radd__", "name": "__radd__", "type": null}}, "__repr__": {".class": "SymbolTableNode", "kind": "Mdef", "node": {".class": "FuncDef", "arg_kinds": [0], "arg_names": ["self"], "flags": [], "fullname": "abjad.pitch.Accidental.Accidental.__repr__", "name": "__repr__", "type": {".class": "CallableType", "arg_kinds": [0], "arg_names": [null], "arg_types": ["abjad.pitch.Accidental.Accidental"], "bound_args": [], "def_extras": {"first_arg": "self"}, "fallback": "builtins.function", "implicit": false, "is_ellipsis_args": false, "name": "__repr__ of Accidental", "ret_type": "builtins.str", "variables": []}}}, "__slots__": {".class": "SymbolTableNode", "kind": "Mdef", "node": {".class": "Var", "flags": ["is_initialized_in_class"], "fullname": "abjad.pitch.Accidental.Accidental.__slots__", "name": "__slots__", "type": {".class": "TupleType", "implicit": false, "items": ["builtins.str", "builtins.str"], "partial_fallback": {".class": "Instance", "args": [{".class": "AnyType", "missing_import_name": null, "source_any": null, "type_of_any": 6}], "type_ref": "builtins.tuple"}}}}, "__str__": {".class": "SymbolTableNode", "kind": "Mdef", "node": {".class": "FuncDef", "arg_kinds": [0], "arg_names": ["self"], "flags": [], "fullname": "abjad.pitch.Accidental.Accidental.__str__", "name": "__str__", "type": null}}, "__sub__": {".class": "SymbolTableNode", "kind": "Mdef", "node": {".class": "FuncDef", "arg_kinds": [0, 0], "arg_names": ["self", "argument"], "flags": [], "fullname": "abjad.pitch.Accidental.Accidental.__sub__", "name": "__sub__", "type": null}}, "_arrow": {".class": "SymbolTableNode", "implicit": true, "kind": "Mdef", "node": {".class": "Var", "flags": [], "fullname": "abjad.pitch.Accidental.Accidental._arrow", "name": "_arrow", "type": {".class": "AnyType", "missing_import_name": null, "source_any": null, "type_of_any": 1}}}, "_get_all_accidental_abbreviations": {".class": "SymbolTableNode", "kind": "Mdef", "node": {".class": "Decorator", "func": {".class": "FuncDef", "arg_kinds": [0], "arg_names": ["class_"], "flags": ["is_class", "is_decorated"], "fullname": "abjad.pitch.Accidental.Accidental._get_all_accidental_abbreviations", "name": "_get_all_accidental_abbreviations", "type": null}, "is_overload": false, "var": {".class": "Var", "flags": ["is_initialized_in_class", "is_classmethod", "is_ready"], "fullname": null, "name": "_get_all_accidental_abbreviations", "type": {".class": "CallableType", "arg_kinds": [0], "arg_names": ["class_"], "arg_types": [{".class": "TypeType", "item": "abjad.pitch.Accidental.Accidental"}], "bound_args": [], "def_extras": {}, "fallback": "builtins.function", "implicit": true, "is_ellipsis_args": false, "name": "_get_all_accidental_abbreviations of Accidental", "ret_type": {".class": "AnyType", "missing_import_name": null, "source_any": null, "type_of_any": 1}, "variables": []}}}}, "_get_all_accidental_names": {".class": "SymbolTableNode", "kind": "Mdef", "node": {".class": "Decorator", "func": {".class": "FuncDef", "arg_kinds": [0], "arg_names": ["class_"], "flags": ["is_class", "is_decorated"], "fullname": "abjad.pitch.Accidental.Accidental._get_all_accidental_names", "name": "_get_all_accidental_names", "type": null}, "is_overload": false, "var": {".class": "Var", "flags": ["is_initialized_in_class", "is_classmethod", "is_ready"], "fullname": null, "name": "_get_all_accidental_names", "type": {".class": "CallableType", "arg_kinds": [0], "arg_names": ["class_"], "arg_types": [{".class": "TypeType", "item": "abjad.pitch.Accidental.Accidental"}], "bound_args": [], "def_extras": {}, "fallback": "builtins.function", "implicit": true, "is_ellipsis_args": false, "name": "_get_all_accidental_names of Accidental", "ret_type": {".class": "AnyType", "missing_import_name": null, "source_any": null, "type_of_any": 1}, "variables": []}}}}, "_get_all_accidental_semitone_values": {".class": "SymbolTableNode", "kind": "Mdef", "node": {".class": "Decorator", "func": {".class": "FuncDef", "arg_kinds": [0], "arg_names": ["class_"], "flags": ["is_class", "is_decorated"], "fullname": "abjad.pitch.Accidental.Accidental._get_all_accidental_semitone_values", "name": "_get_all_accidental_semitone_values", "type": null}, "is_overload": false, "var": {".class": "Var", "flags": ["is_initialized_in_class", "is_classmethod", "is_ready"], "fullname": null, "name": "_get_all_accidental_semitone_values", "type": {".class": "CallableType", "arg_kinds": [0], "arg_names": ["class_"], "arg_types": [{".class": "TypeType", "item": "abjad.pitch.Accidental.Accidental"}], "bound_args": [], "def_extras": {}, "fallback": "builtins.function", "implicit": true, "is_ellipsis_args": false, "name": "_get_all_accidental_semitone_values of Accidental", "ret_type": {".class": "AnyType", "missing_import_name": null, "source_any": null, "type_of_any": 1}, "variables": []}}}}, "_get_format_specification": {".class": "SymbolTableNode", "kind": "Mdef", "node": {".class": "FuncDef", "arg_kinds": [0], "arg_names": ["self"], "flags": [], "fullname": "abjad.pitch.Accidental.Accidental._get_format_specification", "name": "_get_format_specification", "type": null}}, "_get_lilypond_format": {".class": "SymbolTableNode", "kind": "Mdef", "node": {".class": "FuncDef", "arg_kinds": [0], "arg_names": ["self"], "flags": [], "fullname": "abjad.pitch.Accidental.Accidental._get_lilypond_format", "name": "_get_lilypond_format", "type": null}}, "_is_abbreviation": {".class": "SymbolTableNode", "kind": "Mdef", "node": {".class": "Decorator", "func": {".class": "FuncDef", "arg_kinds": [0, 0], "arg_names": ["class_", "argument"], "flags": ["is_class", "is_decorated"], "fullname": "abjad.pitch.Accidental.Accidental._is_abbreviation", "name": "_is_abbreviation", "type": null}, "is_overload": false, "var": {".class": "Var", "flags": ["is_initialized_in_class", "is_classmethod", "is_ready"], "fullname": null, "name": "_is_abbreviation", "type": {".class": "CallableType", "arg_kinds": [0, 0], "arg_names": ["class_", "argument"], "arg_types": [{".class": "TypeType", "item": "abjad.pitch.Accidental.Accidental"}, {".class": "AnyType", "missing_import_name": null, "source_any": null, "type_of_any": 1}], "bound_args": [], "def_extras": {}, "fallback": "builtins.function", "implicit": true, "is_ellipsis_args": false, "name": "_is_abbreviation of Accidental", "ret_type": {".class": "AnyType", "missing_import_name": null, "source_any": null, "type_of_any": 1}, "variables": []}}}}, "_is_symbol": {".class": "SymbolTableNode", "kind": "Mdef", "node": {".class": "Decorator", "func": {".class": "FuncDef", "arg_kinds": [0, 0], "arg_names": ["class_", "argument"], "flags": ["is_class", "is_decorated"], "fullname": "abjad.pitch.Accidental.Accidental._is_symbol", "name": "_is_symbol", "type": null}, "is_overload": false, "var": {".class": "Var", "flags": ["is_initialized_in_class", "is_classmethod", "is_ready"], "fullname": null, "name": "_is_symbol", "type": {".class": "CallableType", "arg_kinds": [0, 0], "arg_names": ["class_", "argument"], "arg_types": [{".class": "TypeType", "item": "abjad.pitch.Accidental.Accidental"}, {".class": "AnyType", "missing_import_name": null, "source_any": null, "type_of_any": 1}], "bound_args": [], "def_extras": {}, "fallback": "builtins.function", "implicit": true, "is_ellipsis_args": false, "name": "_is_symbol of Accidental", "ret_type": {".class": "AnyType", "missing_import_name": null, "source_any": null, "type_of_any": 1}, "variables": []}}}}, "_semitones": {".class": "SymbolTableNode", "implicit": true, "kind": "Mdef", "node": {".class": "Var", "flags": [], "fullname": "abjad.pitch.Accidental.Accidental._semitones", "name": "_semitones", "type": {".class": "AnyType", "missing_import_name": null, "source_any": null, "type_of_any": 1}}}, "arrow": {".class": "SymbolTableNode", "kind": "Mdef", "node": {".class": "Decorator", "func": {".class": "FuncDef", "arg_kinds": [0], "arg_names": ["self"], "flags": ["is_property", "is_decorated"], "fullname": "abjad.pitch.Accidental.Accidental.arrow", "name": "arrow", "type": null}, "is_overload": false, "var": {".class": "Var", "flags": ["is_initialized_in_class", "is_property", "is_ready"], "fullname": null, "name": "arrow", "type": {".class": "CallableType", "arg_kinds": [0], "arg_names": ["self"], "arg_types": ["abjad.pitch.Accidental.Accidental"], "bound_args": [], "def_extras": {}, "fallback": "builtins.function", "implicit": true, "is_ellipsis_args": false, "name": "arrow of Accidental", "ret_type": {".class": "AnyType", "missing_import_name": null, "source_any": null, "type_of_any": 1}, "variables": []}}}}, "name": {".class": "SymbolTableNode", "kind": "Mdef", "node": {".class": "Decorator", "func": {".class": "FuncDef", "arg_kinds": [0], "arg_names": ["self"], "flags": ["is_property", "is_decorated"], "fullname": "abjad.pitch.Accidental.Accidental.name", "name": "name", "type": null}, "is_overload": false, "var": {".class": "Var", "flags": ["is_initialized_in_class", "is_property", "is_ready"], "fullname": null, "name": "name", "type": {".class": "CallableType", "arg_kinds": [0], "arg_names": ["self"], "arg_types": ["abjad.pitch.Accidental.Accidental"], "bound_args": [], "def_extras": {}, "fallback": "builtins.function", "implicit": true, "is_ellipsis_args": false, "name": "name of Accidental", "ret_type": {".class": "AnyType", "missing_import_name": null, "source_any": null, "type_of_any": 1}, "variables": []}}}}, "respell_with_flats": {".class": "SymbolTableNode", "kind": "Mdef", "node": {".class": "Decorator", "func": {".class": "FuncDef", "arg_kinds": [0], "arg_names": ["selection"], "flags": ["is_static", "is_decorated"], "fullname": "abjad.pitch.Accidental.Accidental.respell_with_flats", "name": "respell_with_flats", "type": null}, "is_overload": false, "var": {".class": "Var", "flags": ["is_initialized_in_class", "is_staticmethod", "is_ready"], "fullname": null, "name": "respell_with_flats", "type": {".class": "CallableType", "arg_kinds": [0], "arg_names": ["selection"], "arg_types": [{".class": "AnyType", "missing_import_name": null, "source_any": null, "type_of_any": 1}], "bound_args": [], "def_extras": {}, "fallback": "builtins.function", "implicit": true, "is_ellipsis_args": false, "name": "respell_with_flats of Accidental", "ret_type": {".class": "AnyType", "missing_import_name": null, "source_any": null, "type_of_any": 1}, "variables": []}}}}, "respell_with_sharps": {".class": "SymbolTableNode", "kind": "Mdef", "node": {".class": "Decorator", "func": {".class": "FuncDef", "arg_kinds": [0], "arg_names": ["selection"], "flags": ["is_static", "is_decorated"], "fullname": "abjad.pitch.Accidental.Accidental.respell_with_sharps", "name": "respell_with_sharps", "type": null}, "is_overload": false, "var": {".class": "Var", "flags": ["is_initialized_in_class", "is_staticmethod", "is_ready"], "fullname": null, "name": "respell_with_sharps", "type": {".class": "CallableType", "arg_kinds": [0], "arg_names": ["selection"], "arg_types": [{".class": "AnyType", "missing_import_name": null, "source_any": null, "type_of_any": 1}], "bound_args": [], "def_extras": {}, "fallback": "builtins.function", "implicit": true, "is_ellipsis_args": false, "name": "respell_with_sharps of Accidental", "ret_type": {".class": "AnyType", "missing_import_name": null, "source_any": null, "type_of_any": 1}, "variables": []}}}}, "semitones": {".class": "SymbolTableNode", "kind": "Mdef", "node": {".class": "Decorator", "func": {".class": "FuncDef", "arg_kinds": [0], "arg_names": ["self"], "flags": ["is_property", "is_decorated"], "fullname": "abjad.pitch.Accidental.Accidental.semitones", "name": "semitones", "type": null}, "is_overload": false, "var": {".class": "Var", "flags": ["is_initialized_in_class", "is_property", "is_ready"], "fullname": null, "name": "semitones", "type": {".class": "CallableType", "arg_kinds": [0], "arg_names": ["self"], "arg_types": ["abjad.pitch.Accidental.Accidental"], "bound_args": [], "def_extras": {}, "fallback": "builtins.function", "implicit": true, "is_ellipsis_args": false, "name": "semitones of Accidental", "ret_type": {".class": "AnyType", "missing_import_name": null, "source_any": null, "type_of_any": 1}, "variables": []}}}}, "symbol": {".class": "SymbolTableNode", "kind": "Mdef", "node": {".class": "Decorator", "func": {".class": "FuncDef", "arg_kinds": [0], "arg_names": ["self"], "flags": ["is_property", "is_decorated"], "fullname": "abjad.pitch.Accidental.Accidental.symbol", "name": "symbol", "type": null}, "is_overload": false, "var": {".class": "Var", "flags": ["is_initialized_in_class", "is_property", "is_ready"], "fullname": null, "name": "symbol", "type": {".class": "CallableType", "arg_kinds": [0], "arg_names": ["self"], "arg_types": ["abjad.pitch.Accidental.Accidental"], "bound_args": [], "def_extras": {}, "fallback": "builtins.function", "implicit": true, "is_ellipsis_args": false, "name": "symbol of Accidental", "ret_type": {".class": "AnyType", "missing_import_name": null, "source_any": null, "type_of_any": 1}, "variables": []}}}}}, "tuple_type": null, "type_vars": [], "typeddict_type": null}}, "FormatSpecification": {".class": "SymbolTableNode", "cross_ref": "abjad.system.FormatSpecification.FormatSpecification", "kind": "Gdef"}, "StorageFormatManager": {".class": "SymbolTableNode", "cross_ref": "abjad.system.StorageFormatManager.StorageFormatManager", "kind": "Gdef"}, "__doc__": {".class": "SymbolTableNode", "kind": "Gdef", "node": {".class": "Var", "flags": ["is_ready"], "fullname": "abjad.pitch.Accidental.__doc__", "name": "__doc__", "type": "builtins.str"}}, "__file__": {".class": "SymbolTableNode", "kind": "Gdef", "node": {".class": "Var", "flags": ["is_ready"], "fullname": "abjad.pitch.Accidental.__file__", "name": "__file__", "type": "builtins.str"}}, "__name__": {".class": "SymbolTableNode", "kind": "Gdef", "node": {".class": "Var", "flags": ["is_ready"], "fullname": "abjad.pitch.Accidental.__name__", "name": "__name__", "type": "builtins.str"}}, "__package__": {".class": "SymbolTableNode", "kind": "Gdef", "node": {".class": "Var", "flags": ["is_ready"], "fullname": "abjad.pitch.Accidental.__package__", "name": "__package__", "type": "builtins.str"}}, "constants": {".class": "SymbolTableNode", "cross_ref": "abjad.pitch.constants", "kind": "Gdef"}, "enums": {".class": "SymbolTableNode", "cross_ref": "abjad.enums", "kind": "Gdef"}, "functools": {".class": "SymbolTableNode", "cross_ref": "functools", "kind": "Gdef"}, "mathtools": {".class": "SymbolTableNode", "cross_ref": "abjad.mathtools", "kind": "Gdef"}, "numbers": {".class": "SymbolTableNode", "cross_ref": "numbers", "kind": "Gdef"}}, "path": "/Users/evansdsg2/abjad/abjad/pitch/Accidental.py"}