{".class": "MypyFile", "_fullname": "abjad.pitch.PitchClassSet", "is_partial_stub_package": false, "is_stub": false, "names": {".class": "SymbolTable", "Enumerator": {".class": "SymbolTableNode", "cross_ref": "abjad.utilities.Enumerator.Enumerator", "kind": "Gdef"}, "PitchClassSet": {".class": "SymbolTableNode", "kind": "Gdef", "node": {".class": "TypeInfo", "_promote": null, "abstract_attributes": [], "bases": ["abjad.pitch.Set.Set"], "declared_metaclass": null, "defn": {".class": "ClassDef", "fullname": "abjad.pitch.PitchClassSet.PitchClassSet", "name": "PitchClassSet", "type_vars": []}, "flags": [], "fullname": "abjad.pitch.PitchClassSet.PitchClassSet", "metaclass_type": "abc.ABCMeta", "metadata": {}, "module_name": "abjad.pitch.PitchClassSet", "mro": ["abjad.pitch.PitchClassSet.PitchClassSet", "abjad.pitch.Set.Set", "abjad.utilities.TypedFrozenset.TypedFrozenset", "abjad.utilities.TypedCollection.TypedCollection", "typing.AbstractSet", "typing.Collection", "typing.Iterable", "typing.Container", "builtins.object"], "names": {".class": "SymbolTable", "__contains__": {".class": "SymbolTableNode", "kind": "Mdef", "node": {".class": "FuncDef", "arg_kinds": [0, 0], "arg_names": ["self", "argument"], "flags": [], "fullname": "abjad.pitch.PitchClassSet.PitchClassSet.__contains__", "name": "__contains__", "type": null}}, "__hash__": {".class": "SymbolTableNode", "kind": "Mdef", "node": {".class": "FuncDef", "arg_kinds": [0], "arg_names": ["self"], "flags": [], "fullname": "abjad.pitch.PitchClassSet.PitchClassSet.__hash__", "name": "__hash__", "type": null}}, "__illustrate__": {".class": "SymbolTableNode", "kind": "Mdef", "node": {".class": "FuncDef", "arg_kinds": [0], "arg_names": ["self"], "flags": [], "fullname": "abjad.pitch.PitchClassSet.PitchClassSet.__illustrate__", "name": "__illustrate__", "type": null}}, "__slots__": {".class": "SymbolTableNode", "kind": "Mdef", "node": {".class": "Var", "flags": ["is_initialized_in_class"], "fullname": "abjad.pitch.PitchClassSet.PitchClassSet.__slots__", "name": "__slots__", "type": {".class": "TupleType", "implicit": false, "items": [], "partial_fallback": {".class": "Instance", "args": [{".class": "AnyType", "missing_import_name": null, "source_any": null, "type_of_any": 6}], "type_ref": "builtins.tuple"}}}}, "__str__": {".class": "SymbolTableNode", "kind": "Mdef", "node": {".class": "FuncDef", "arg_kinds": [0], "arg_names": ["self"], "flags": [], "fullname": "abjad.pitch.PitchClassSet.PitchClassSet.__str__", "name": "__str__", "type": null}}, "_get_most_compact_ordering": {".class": "SymbolTableNode", "kind": "Mdef", "node": {".class": "Decorator", "func": {".class": "FuncDef", "arg_kinds": [0], "arg_names": ["candidates"], "flags": ["is_static", "is_decorated"], "fullname": "abjad.pitch.PitchClassSet.PitchClassSet._get_most_compact_ordering", "name": "_get_most_compact_ordering", "type": null}, "is_overload": false, "var": {".class": "Var", "flags": ["is_initialized_in_class", "is_staticmethod", "is_ready"], "fullname": null, "name": "_get_most_compact_ordering", "type": {".class": "CallableType", "arg_kinds": [0], "arg_names": ["candidates"], "arg_types": [{".class": "AnyType", "missing_import_name": null, "source_any": null, "type_of_any": 1}], "bound_args": [], "def_extras": {}, "fallback": "builtins.function", "implicit": true, "is_ellipsis_args": false, "name": "_get_most_compact_ordering of PitchClassSet", "ret_type": {".class": "AnyType", "missing_import_name": null, "source_any": null, "type_of_any": 1}, "variables": []}}}}, "_named_item_class": {".class": "SymbolTableNode", "kind": "Mdef", "node": {".class": "Decorator", "func": {".class": "FuncDef", "arg_kinds": [0], "arg_names": ["self"], "flags": ["is_property", "is_decorated"], "fullname": "abjad.pitch.PitchClassSet.PitchClassSet._named_item_class", "name": "_named_item_class", "type": null}, "is_overload": false, "var": {".class": "Var", "flags": ["is_initialized_in_class", "is_property", "is_ready"], "fullname": null, "name": "_named_item_class", "type": {".class": "CallableType", "arg_kinds": [0], "arg_names": ["self"], "arg_types": ["abjad.pitch.PitchClassSet.PitchClassSet"], "bound_args": [], "def_extras": {}, "fallback": "builtins.function", "implicit": true, "is_ellipsis_args": false, "name": "_named_item_class of PitchClassSet", "ret_type": {".class": "AnyType", "missing_import_name": null, "source_any": null, "type_of_any": 1}, "variables": []}}}}, "_numbered_item_class": {".class": "SymbolTableNode", "kind": "Mdef", "node": {".class": "Decorator", "func": {".class": "FuncDef", "arg_kinds": [0], "arg_names": ["self"], "flags": ["is_property", "is_decorated"], "fullname": "abjad.pitch.PitchClassSet.PitchClassSet._numbered_item_class", "name": "_numbered_item_class", "type": null}, "is_overload": false, "var": {".class": "Var", "flags": ["is_initialized_in_class", "is_property", "is_ready"], "fullname": null, "name": "_numbered_item_class", "type": {".class": "CallableType", "arg_kinds": [0], "arg_names": ["self"], "arg_types": ["abjad.pitch.PitchClassSet.PitchClassSet"], "bound_args": [], "def_extras": {}, "fallback": "builtins.function", "implicit": true, "is_ellipsis_args": false, "name": "_numbered_item_class of PitchClassSet", "ret_type": {".class": "AnyType", "missing_import_name": null, "source_any": null, "type_of_any": 1}, "variables": []}}}}, "_parent_item_class": {".class": "SymbolTableNode", "kind": "Mdef", "node": {".class": "Decorator", "func": {".class": "FuncDef", "arg_kinds": [0], "arg_names": ["self"], "flags": ["is_property", "is_decorated"], "fullname": "abjad.pitch.PitchClassSet.PitchClassSet._parent_item_class", "name": "_parent_item_class", "type": null}, "is_overload": false, "var": {".class": "Var", "flags": ["is_initialized_in_class", "is_property", "is_ready"], "fullname": null, "name": "_parent_item_class", "type": {".class": "CallableType", "arg_kinds": [0], "arg_names": ["self"], "arg_types": ["abjad.pitch.PitchClassSet.PitchClassSet"], "bound_args": [], "def_extras": {}, "fallback": "builtins.function", "implicit": true, "is_ellipsis_args": false, "name": "_parent_item_class of PitchClassSet", "ret_type": {".class": "AnyType", "missing_import_name": null, "source_any": null, "type_of_any": 1}, "variables": []}}}}, "from_selection": {".class": "SymbolTableNode", "kind": "Mdef", "node": {".class": "Decorator", "func": {".class": "FuncDef", "arg_kinds": [0, 0, 1], "arg_names": ["class_", "selection", "item_class"], "flags": ["is_class", "is_decorated"], "fullname": "abjad.pitch.PitchClassSet.PitchClassSet.from_selection", "name": "from_selection", "type": null}, "is_overload": false, "var": {".class": "Var", "flags": ["is_initialized_in_class", "is_classmethod", "is_ready"], "fullname": null, "name": "from_selection", "type": {".class": "CallableType", "arg_kinds": [0, 0, 1], "arg_names": ["class_", "selection", "item_class"], "arg_types": [{".class": "TypeType", "item": "abjad.pitch.PitchClassSet.PitchClassSet"}, {".class": "AnyType", "missing_import_name": null, "source_any": null, "type_of_any": 1}, {".class": "AnyType", "missing_import_name": null, "source_any": null, "type_of_any": 1}], "bound_args": [], "def_extras": {}, "fallback": "builtins.function", "implicit": true, "is_ellipsis_args": false, "name": "from_selection of PitchClassSet", "ret_type": {".class": "AnyType", "missing_import_name": null, "source_any": null, "type_of_any": 1}, "variables": []}}}}, "get_normal_order": {".class": "SymbolTableNode", "kind": "Mdef", "node": {".class": "FuncDef", "arg_kinds": [0], "arg_names": ["self"], "flags": [], "fullname": "abjad.pitch.PitchClassSet.PitchClassSet.get_normal_order", "name": "get_normal_order", "type": null}}, "get_prime_form": {".class": "SymbolTableNode", "kind": "Mdef", "node": {".class": "FuncDef", "arg_kinds": [0, 1], "arg_names": ["self", "transposition_only"], "flags": [], "fullname": "abjad.pitch.PitchClassSet.PitchClassSet.get_prime_form", "name": "get_prime_form", "type": null}}, "invert": {".class": "SymbolTableNode", "kind": "Mdef", "node": {".class": "FuncDef", "arg_kinds": [0, 1], "arg_names": ["self", "axis"], "flags": [], "fullname": "abjad.pitch.PitchClassSet.PitchClassSet.invert", "name": "invert", "type": null}}, "is_transposed_subset": {".class": "SymbolTableNode", "kind": "Mdef", "node": {".class": "FuncDef", "arg_kinds": [0, 0], "arg_names": ["self", "pcset"], "flags": [], "fullname": "abjad.pitch.PitchClassSet.PitchClassSet.is_transposed_subset", "name": "is_transposed_subset", "type": null}}, "is_transposed_superset": {".class": "SymbolTableNode", "kind": "Mdef", "node": {".class": "FuncDef", "arg_kinds": [0, 0], "arg_names": ["self", "pcset"], "flags": [], "fullname": "abjad.pitch.PitchClassSet.PitchClassSet.is_transposed_superset", "name": "is_transposed_superset", "type": null}}, "multiply": {".class": "SymbolTableNode", "kind": "Mdef", "node": {".class": "FuncDef", "arg_kinds": [0, 0], "arg_names": ["self", "n"], "flags": [], "fullname": "abjad.pitch.PitchClassSet.PitchClassSet.multiply", "name": "multiply", "type": null}}, "order_by": {".class": "SymbolTableNode", "kind": "Mdef", "node": {".class": "FuncDef", "arg_kinds": [0, 0], "arg_names": ["self", "segment"], "flags": [], "fullname": "abjad.pitch.PitchClassSet.PitchClassSet.order_by", "name": "order_by", "type": null}}, "transpose": {".class": "SymbolTableNode", "kind": "Mdef", "node": {".class": "FuncDef", "arg_kinds": [0, 1], "arg_names": ["self", "n"], "flags": [], "fullname": "abjad.pitch.PitchClassSet.PitchClassSet.transpose", "name": "transpose", "type": null}}}, "tuple_type": null, "type_vars": [], "typeddict_type": null}}, "Set": {".class": "SymbolTableNode", "cross_ref": "abjad.pitch.Set.Set", "kind": "Gdef"}, "__doc__": {".class": "SymbolTableNode", "kind": "Gdef", "node": {".class": "Var", "flags": ["is_ready"], "fullname": "abjad.pitch.PitchClassSet.__doc__", "name": "__doc__", "type": "builtins.str"}}, "__file__": {".class": "SymbolTableNode", "kind": "Gdef", "node": {".class": "Var", "flags": ["is_ready"], "fullname": "abjad.pitch.PitchClassSet.__file__", "name": "__file__", "type": "builtins.str"}}, "__name__": {".class": "SymbolTableNode", "kind": "Gdef", "node": {".class": "Var", "flags": ["is_ready"], "fullname": "abjad.pitch.PitchClassSet.__name__", "name": "__name__", "type": "builtins.str"}}, "__package__": {".class": "SymbolTableNode", "kind": "Gdef", "node": {".class": "Var", "flags": ["is_ready"], "fullname": "abjad.pitch.PitchClassSet.__package__", "name": "__package__", "type": "builtins.str"}}, "copy": {".class": "SymbolTableNode", "cross_ref": "copy", "kind": "Gdef"}}, "path": "/Users/evansdsg2/abjad/abjad/pitch/PitchClassSet.py"}