{"data_mtime": 1590763888, "dep_lines": [1, 2, 3, 5, 5, 6, 7, 8, 1, 1, 1, 1, 1, 1, 1, 1, 1, 1, 1, 1, 1, 1, 1], "dep_prios": [10, 10, 10, 20, 10, 5, 5, 5, 5, 20, 20, 20, 20, 20, 20, 20, 20, 20, 20, 20, 20, 30, 30], "dependencies": ["abc", "collections", "types", "abjad", "abjad.mathtools", "abjad.system.FormatSpecification", "abjad.utilities.TypedCollection", "abjad.utilities.TypedCounter", "builtins", "typing", "abjad.markups", "functools", "re", "abjad.rhythmtrees", "abjad.enums", "abjad.indicators", "copy", "bisect", "numbers", "abjad.system", "abjad.typings", "abjad.utilities", "collections.abc"], "hash": "c7991a475372847878e0d23ac0c9bf70d9d35fd62b890d3a9830bed2376e3049", "id": "abjad.pitch.Vector", "ignore_all": false, "interface_hash": "e2ffc889075df87be8cfe47ae5636ff28c1cb37c0eb7fc7cb13252a3386afcb0", "mtime": 1578099312, "options": {"allow_redefinition": false, "allow_untyped_globals": false, "always_false": [], "always_true": [], "bazel": false, "check_untyped_defs": false, "disallow_any_decorated": false, "disallow_any_explicit": false, "disallow_any_expr": false, "disallow_any_generics": false, "disallow_any_unimported": false, "disallow_incomplete_defs": false, "disallow_subclassing_any": false, "disallow_untyped_calls": false, "disallow_untyped_decorators": false, "disallow_untyped_defs": false, "follow_imports": "normal", "follow_imports_for_stubs": false, "ignore_errors": false, "ignore_missing_imports": false, "implicit_reexport": true, "local_partial_types": false, "mypyc": false, "no_implicit_optional": false, "platform": "darwin", "plugins": [], "show_none_errors": true, "strict_equality": false, "strict_optional": true, "strict_optional_whitelist": null, "warn_no_return": true, "warn_return_any": false, "warn_unreachable": false, "warn_unused_ignores": false}, "path": "/Users/evansdsg2/abjad/abjad/pitch/Vector.py", "plugin_data": null, "size": 4230, "suppressed": [], "version_id": "0.770"}