{".class": "MypyFile", "_fullname": "abjad.scheme", "is_partial_stub_package": false, "is_stub": false, "names": {".class": "SymbolTable", "FormatSpecification": {".class": "SymbolTableNode", "cross_ref": "abjad.system.FormatSpecification.FormatSpecification", "kind": "Gdef"}, "NonreducedFraction": {".class": "SymbolTableNode", "cross_ref": "abjad.mathtools.NonreducedFraction", "kind": "Gdef"}, "Scheme": {".class": "SymbolTableNode", "kind": "Gdef", "node": {".class": "TypeInfo", "_promote": null, "abstract_attributes": [], "bases": ["builtins.object"], "declared_metaclass": null, "defn": {".class": "ClassDef", "fullname": "abjad.scheme.Scheme", "name": "Scheme", "type_vars": []}, "flags": [], "fullname": "abjad.scheme.Scheme", "metaclass_type": null, "metadata": {}, "module_name": "abjad.scheme", "mro": ["abjad.scheme.Scheme", "builtins.object"], "names": {".class": "SymbolTable", "__eq__": {".class": "SymbolTableNode", "kind": "Mdef", "node": {".class": "FuncDef", "arg_kinds": [0, 0], "arg_names": ["self", "argument"], "flags": [], "fullname": "abjad.scheme.Scheme.__eq__", "name": "__eq__", "type": {".class": "CallableType", "arg_kinds": [0, 0], "arg_names": [null, null], "arg_types": ["abjad.scheme.Scheme", {".class": "AnyType", "missing_import_name": null, "source_any": null, "type_of_any": 1}], "bound_args": [], "def_extras": {"first_arg": "self"}, "fallback": "builtins.function", "implicit": false, "is_ellipsis_args": false, "name": "__eq__ of Scheme", "ret_type": "builtins.bool", "variables": []}}}, "__format__": {".class": "SymbolTableNode", "kind": "Mdef", "node": {".class": "FuncDef", "arg_kinds": [0, 1], "arg_names": ["self", "format_specification"], "flags": [], "fullname": "abjad.scheme.Scheme.__format__", "name": "__format__", "type": {".class": "CallableType", "arg_kinds": [0, 1], "arg_names": ["self", "format_specification"], "arg_types": ["abjad.scheme.Scheme", {".class": "AnyType", "missing_import_name": null, "source_any": null, "type_of_any": 1}], "bound_args": [], "def_extras": {"first_arg": "self"}, "fallback": "builtins.function", "implicit": false, "is_ellipsis_args": false, "name": "__format__ of Scheme", "ret_type": "builtins.str", "variables": []}}}, "__init__": {".class": "SymbolTableNode", "kind": "Mdef", "node": {".class": "FuncDef", "arg_kinds": [0, 1, 1, 1, 1], "arg_names": ["self", "value", "force_quotes", "quoting", "verbatim"], "flags": [], "fullname": "abjad.scheme.Scheme.__init__", "name": "__init__", "type": {".class": "CallableType", "arg_kinds": [0, 1, 1, 1, 1], "arg_names": ["self", "value", "force_quotes", "quoting", "verbatim"], "arg_types": ["abjad.scheme.Scheme", {".class": "UnionType", "items": [{".class": "AnyType", "missing_import_name": null, "source_any": null, "type_of_any": 2}, {".class": "NoneType"}]}, {".class": "UnionType", "items": ["builtins.bool", {".class": "NoneType"}]}, {".class": "UnionType", "items": ["builtins.str", {".class": "NoneType"}]}, {".class": "UnionType", "items": ["builtins.bool", {".class": "NoneType"}]}], "bound_args": [], "def_extras": {"first_arg": "self"}, "fallback": "builtins.function", "implicit": false, "is_ellipsis_args": false, "name": "__init__ of Scheme", "ret_type": {".class": "NoneType"}, "variables": []}}}, "__repr__": {".class": "SymbolTableNode", "kind": "Mdef", "node": {".class": "FuncDef", "arg_kinds": [0], "arg_names": ["self"], "flags": [], "fullname": "abjad.scheme.Scheme.__repr__", "name": "__repr__", "type": {".class": "CallableType", "arg_kinds": [0], "arg_names": [null], "arg_types": ["abjad.scheme.Scheme"], "bound_args": [], "def_extras": {"first_arg": "self"}, "fallback": "builtins.function", "implicit": false, "is_ellipsis_args": false, "name": "__repr__ of Scheme", "ret_type": "builtins.str", "variables": []}}}, "__slots__": {".class": "SymbolTableNode", "kind": "Mdef", "node": {".class": "Var", "flags": ["is_initialized_in_class"], "fullname": "abjad.scheme.Scheme.__slots__", "name": "__slots__", "type": {".class": "TupleType", "implicit": false, "items": ["builtins.str", "builtins.str", "builtins.str", "builtins.str"], "partial_fallback": {".class": "Instance", "args": [{".class": "AnyType", "missing_import_name": null, "source_any": null, "type_of_any": 6}], "type_ref": "builtins.tuple"}}}}, "__str__": {".class": "SymbolTableNode", "kind": "Mdef", "node": {".class": "FuncDef", "arg_kinds": [0], "arg_names": ["self"], "flags": [], "fullname": "abjad.scheme.Scheme.__str__", "name": "__str__", "type": {".class": "CallableType", "arg_kinds": [0], "arg_names": [null], "arg_types": ["abjad.scheme.Scheme"], "bound_args": [], "def_extras": {"first_arg": "self"}, "fallback": "builtins.function", "implicit": false, "is_ellipsis_args": false, "name": "__str__ of Scheme", "ret_type": "builtins.str", "variables": []}}}, "_force_quotes": {".class": "SymbolTableNode", "implicit": true, "kind": "Mdef", "node": {".class": "Var", "flags": [], "fullname": "abjad.scheme.Scheme._force_quotes", "name": "_force_quotes", "type": {".class": "UnionType", "items": ["builtins.bool", {".class": "NoneType"}]}}}, "_get_format_specification": {".class": "SymbolTableNode", "kind": "Mdef", "node": {".class": "FuncDef", "arg_kinds": [0], "arg_names": ["self"], "flags": [], "fullname": "abjad.scheme.Scheme._get_format_specification", "name": "_get_format_specification", "type": null}}, "_get_formatted_value": {".class": "SymbolTableNode", "kind": "Mdef", "node": {".class": "FuncDef", "arg_kinds": [0], "arg_names": ["self"], "flags": [], "fullname": "abjad.scheme.Scheme._get_formatted_value", "name": "_get_formatted_value", "type": null}}, "_get_lilypond_format": {".class": "SymbolTableNode", "kind": "Mdef", "node": {".class": "FuncDef", "arg_kinds": [0], "arg_names": ["self"], "flags": [], "fullname": "abjad.scheme.Scheme._get_lilypond_format", "name": "_get_lilypond_format", "type": null}}, "_publish_storage_format": {".class": "SymbolTableNode", "kind": "Mdef", "node": {".class": "Var", "flags": ["is_initialized_in_class"], "fullname": "abjad.scheme.Scheme._publish_storage_format", "name": "_publish_storage_format", "type": "builtins.bool"}}, "_quoting": {".class": "SymbolTableNode", "implicit": true, "kind": "Mdef", "node": {".class": "Var", "flags": [], "fullname": "abjad.scheme.Scheme._quoting", "name": "_quoting", "type": {".class": "UnionType", "items": ["builtins.str", {".class": "NoneType"}]}}}, "_value": {".class": "SymbolTableNode", "implicit": true, "kind": "Mdef", "node": {".class": "Var", "flags": [], "fullname": "abjad.scheme.Scheme._value", "name": "_value", "type": {".class": "UnionType", "items": [{".class": "AnyType", "missing_import_name": null, "source_any": null, "type_of_any": 2}, {".class": "NoneType"}]}}}, "_verbatim": {".class": "SymbolTableNode", "implicit": true, "kind": "Mdef", "node": {".class": "Var", "flags": [], "fullname": "abjad.scheme.Scheme._verbatim", "name": "_verbatim", "type": {".class": "UnionType", "items": ["builtins.bool", {".class": "NoneType"}]}}}, "force_quotes": {".class": "SymbolTableNode", "kind": "Mdef", "node": {".class": "Decorator", "func": {".class": "FuncDef", "arg_kinds": [0], "arg_names": ["self"], "flags": ["is_property", "is_decorated"], "fullname": "abjad.scheme.Scheme.force_quotes", "name": "force_quotes", "type": {".class": "CallableType", "arg_kinds": [0], "arg_names": ["self"], "arg_types": ["abjad.scheme.Scheme"], "bound_args": [], "def_extras": {"first_arg": "self"}, "fallback": "builtins.function", "implicit": false, "is_ellipsis_args": false, "name": "force_quotes of Scheme", "ret_type": {".class": "UnionType", "items": ["builtins.bool", {".class": "NoneType"}]}, "variables": []}}, "is_overload": false, "var": {".class": "Var", "flags": ["is_initialized_in_class", "is_property", "is_ready"], "fullname": null, "name": "force_quotes", "type": {".class": "CallableType", "arg_kinds": [0], "arg_names": ["self"], "arg_types": ["abjad.scheme.Scheme"], "bound_args": [], "def_extras": {"first_arg": "self"}, "fallback": "builtins.function", "implicit": false, "is_ellipsis_args": false, "name": "force_quotes of Scheme", "ret_type": {".class": "UnionType", "items": ["builtins.bool", {".class": "NoneType"}]}, "variables": []}}}}, "format_embedded_scheme_value": {".class": "SymbolTableNode", "kind": "Mdef", "node": {".class": "Decorator", "func": {".class": "FuncDef", "arg_kinds": [0, 1], "arg_names": ["value", "force_quotes"], "flags": ["is_static", "is_decorated"], "fullname": "abjad.scheme.Scheme.format_embedded_scheme_value", "name": "format_embedded_scheme_value", "type": {".class": "CallableType", "arg_kinds": [0, 1], "arg_names": ["value", "force_quotes"], "arg_types": [{".class": "AnyType", "missing_import_name": null, "source_any": null, "type_of_any": 2}, "builtins.bool"], "bound_args": [], "def_extras": {"first_arg": null}, "fallback": "builtins.function", "implicit": false, "is_ellipsis_args": false, "name": "format_embedded_scheme_value of Scheme", "ret_type": "builtins.str", "variables": []}}, "is_overload": false, "var": {".class": "Var", "flags": ["is_initialized_in_class", "is_staticmethod", "is_ready"], "fullname": null, "name": "format_embedded_scheme_value", "type": {".class": "CallableType", "arg_kinds": [0, 1], "arg_names": ["value", "force_quotes"], "arg_types": [{".class": "AnyType", "missing_import_name": null, "source_any": null, "type_of_any": 2}, "builtins.bool"], "bound_args": [], "def_extras": {"first_arg": null}, "fallback": "builtins.function", "implicit": false, "is_ellipsis_args": false, "name": "format_embedded_scheme_value of Scheme", "ret_type": "builtins.str", "variables": []}}}}, "format_scheme_value": {".class": "SymbolTableNode", "kind": "Mdef", "node": {".class": "Decorator", "func": {".class": "FuncDef", "arg_kinds": [0, 1, 1], "arg_names": ["value", "force_quotes", "verbatim"], "flags": ["is_static", "is_decorated"], "fullname": "abjad.scheme.Scheme.format_scheme_value", "name": "format_scheme_value", "type": {".class": "CallableType", "arg_kinds": [0, 1, 1], "arg_names": ["value", "force_quotes", "verbatim"], "arg_types": [{".class": "AnyType", "missing_import_name": null, "source_any": null, "type_of_any": 2}, "builtins.bool", "builtins.bool"], "bound_args": [], "def_extras": {"first_arg": null}, "fallback": "builtins.function", "implicit": false, "is_ellipsis_args": false, "name": "format_scheme_value of Scheme", "ret_type": "builtins.str", "variables": []}}, "is_overload": false, "var": {".class": "Var", "flags": ["is_initialized_in_class", "is_staticmethod", "is_ready"], "fullname": null, "name": "format_scheme_value", "type": {".class": "CallableType", "arg_kinds": [0, 1, 1], "arg_names": ["value", "force_quotes", "verbatim"], "arg_types": [{".class": "AnyType", "missing_import_name": null, "source_any": null, "type_of_any": 2}, "builtins.bool", "builtins.bool"], "bound_args": [], "def_extras": {"first_arg": null}, "fallback": "builtins.function", "implicit": false, "is_ellipsis_args": false, "name": "format_scheme_value of Scheme", "ret_type": "builtins.str", "variables": []}}}}, "lilypond_color_constants": {".class": "SymbolTableNode", "kind": "Mdef", "node": {".class": "Var", "flags": ["is_initialized_in_class"], "fullname": "abjad.scheme.Scheme.lilypond_color_constants", "name": "lilypond_color_constants", "type": {".class": "TupleType", "implicit": false, "items": ["builtins.str", "builtins.str", "builtins.str", "builtins.str", "builtins.str", "builtins.str", "builtins.str", "builtins.str", "builtins.str", "builtins.str", "builtins.str", "builtins.str", "builtins.str", "builtins.str", "builtins.str", "builtins.str", "builtins.str", "builtins.str", "builtins.str", "builtins.str"], "partial_fallback": {".class": "Instance", "args": [{".class": "AnyType", "missing_import_name": null, "source_any": null, "type_of_any": 6}], "type_ref": "builtins.tuple"}}}}, "quoting": {".class": "SymbolTableNode", "kind": "Mdef", "node": {".class": "Decorator", "func": {".class": "FuncDef", "arg_kinds": [0], "arg_names": ["self"], "flags": ["is_property", "is_decorated"], "fullname": "abjad.scheme.Scheme.quoting", "name": "quoting", "type": {".class": "CallableType", "arg_kinds": [0], "arg_names": ["self"], "arg_types": ["abjad.scheme.Scheme"], "bound_args": [], "def_extras": {"first_arg": "self"}, "fallback": "builtins.function", "implicit": false, "is_ellipsis_args": false, "name": "quoting of Scheme", "ret_type": {".class": "UnionType", "items": ["builtins.str", {".class": "NoneType"}]}, "variables": []}}, "is_overload": false, "var": {".class": "Var", "flags": ["is_initialized_in_class", "is_property", "is_ready"], "fullname": null, "name": "quoting", "type": {".class": "CallableType", "arg_kinds": [0], "arg_names": ["self"], "arg_types": ["abjad.scheme.Scheme"], "bound_args": [], "def_extras": {"first_arg": "self"}, "fallback": "builtins.function", "implicit": false, "is_ellipsis_args": false, "name": "quoting of Scheme", "ret_type": {".class": "UnionType", "items": ["builtins.str", {".class": "NoneType"}]}, "variables": []}}}}, "value": {".class": "SymbolTableNode", "kind": "Mdef", "node": {".class": "Decorator", "func": {".class": "FuncDef", "arg_kinds": [0], "arg_names": ["self"], "flags": ["is_property", "is_decorated"], "fullname": "abjad.scheme.Scheme.value", "name": "value", "type": {".class": "CallableType", "arg_kinds": [0], "arg_names": ["self"], "arg_types": ["abjad.scheme.Scheme"], "bound_args": [], "def_extras": {"first_arg": "self"}, "fallback": "builtins.function", "implicit": false, "is_ellipsis_args": false, "name": "value of Scheme", "ret_type": {".class": "AnyType", "missing_import_name": null, "source_any": null, "type_of_any": 2}, "variables": []}}, "is_overload": false, "var": {".class": "Var", "flags": ["is_initialized_in_class", "is_property", "is_ready"], "fullname": null, "name": "value", "type": {".class": "CallableType", "arg_kinds": [0], "arg_names": ["self"], "arg_types": ["abjad.scheme.Scheme"], "bound_args": [], "def_extras": {"first_arg": "self"}, "fallback": "builtins.function", "implicit": false, "is_ellipsis_args": false, "name": "value of Scheme", "ret_type": {".class": "AnyType", "missing_import_name": null, "source_any": null, "type_of_any": 2}, "variables": []}}}}, "verbatim": {".class": "SymbolTableNode", "kind": "Mdef", "node": {".class": "Decorator", "func": {".class": "FuncDef", "arg_kinds": [0], "arg_names": ["self"], "flags": ["is_property", "is_decorated"], "fullname": "abjad.scheme.Scheme.verbatim", "name": "verbatim", "type": {".class": "CallableType", "arg_kinds": [0], "arg_names": ["self"], "arg_types": ["abjad.scheme.Scheme"], "bound_args": [], "def_extras": {"first_arg": "self"}, "fallback": "builtins.function", "implicit": false, "is_ellipsis_args": false, "name": "verbatim of Scheme", "ret_type": {".class": "UnionType", "items": ["builtins.bool", {".class": "NoneType"}]}, "variables": []}}, "is_overload": false, "var": {".class": "Var", "flags": ["is_initialized_in_class", "is_property", "is_ready"], "fullname": null, "name": "verbatim", "type": {".class": "CallableType", "arg_kinds": [0], "arg_names": ["self"], "arg_types": ["abjad.scheme.Scheme"], "bound_args": [], "def_extras": {"first_arg": "self"}, "fallback": "builtins.function", "implicit": false, "is_ellipsis_args": false, "name": "verbatim of Scheme", "ret_type": {".class": "UnionType", "items": ["builtins.bool", {".class": "NoneType"}]}, "variables": []}}}}}, "tuple_type": null, "type_vars": [], "typeddict_type": null}}, "SchemeAssociativeList": {".class": "SymbolTableNode", "kind": "Gdef", "node": {".class": "TypeInfo", "_promote": null, "abstract_attributes": [], "bases": ["abjad.scheme.Scheme"], "declared_metaclass": null, "defn": {".class": "ClassDef", "fullname": "abjad.scheme.SchemeAssociativeList", "name": "SchemeAssociativeList", "type_vars": []}, "flags": [], "fullname": "abjad.scheme.SchemeAssociativeList", "metaclass_type": null, "metadata": {}, "module_name": "abjad.scheme", "mro": ["abjad.scheme.SchemeAssociativeList", "abjad.scheme.Scheme", "builtins.object"], "names": {".class": "SymbolTable", "__init__": {".class": "SymbolTableNode", "kind": "Mdef", "node": {".class": "FuncDef", "arg_kinds": [0, 1], "arg_names": ["self", "value"], "flags": [], "fullname": "abjad.scheme.SchemeAssociativeList.__init__", "name": "__init__", "type": {".class": "CallableType", "arg_kinds": [0, 1], "arg_names": ["self", "value"], "arg_types": ["abjad.scheme.SchemeAssociativeList", {".class": "UnionType", "items": [{".class": "Instance", "args": [{".class": "AnyType", "missing_import_name": null, "source_any": null, "type_of_any": 4}], "type_ref": "builtins.list"}, {".class": "NoneType"}]}], "bound_args": [], "def_extras": {"first_arg": "self"}, "fallback": "builtins.function", "implicit": false, "is_ellipsis_args": false, "name": "__init__ of SchemeAssociativeList", "ret_type": {".class": "NoneType"}, "variables": []}}}, "__slots__": {".class": "SymbolTableNode", "kind": "Mdef", "node": {".class": "Var", "flags": ["is_initialized_in_class"], "fullname": "abjad.scheme.SchemeAssociativeList.__slots__", "name": "__slots__", "type": {".class": "TupleType", "implicit": false, "items": [], "partial_fallback": {".class": "Instance", "args": [{".class": "AnyType", "missing_import_name": null, "source_any": null, "type_of_any": 6}], "type_ref": "builtins.tuple"}}}}}, "tuple_type": null, "type_vars": [], "typeddict_type": null}}, "SchemeColor": {".class": "SymbolTableNode", "kind": "Gdef", "node": {".class": "TypeInfo", "_promote": null, "abstract_attributes": [], "bases": ["abjad.scheme.Scheme"], "declared_metaclass": null, "defn": {".class": "ClassDef", "fullname": "abjad.scheme.SchemeColor", "name": "SchemeColor", "type_vars": []}, "flags": [], "fullname": "abjad.scheme.SchemeColor", "metaclass_type": null, "metadata": {}, "module_name": "abjad.scheme", "mro": ["abjad.scheme.SchemeColor", "abjad.scheme.Scheme", "builtins.object"], "names": {".class": "SymbolTable", "__slots__": {".class": "SymbolTableNode", "kind": "Mdef", "node": {".class": "Var", "flags": ["is_initialized_in_class"], "fullname": "abjad.scheme.SchemeColor.__slots__", "name": "__slots__", "type": {".class": "TupleType", "implicit": false, "items": [], "partial_fallback": {".class": "Instance", "args": [{".class": "AnyType", "missing_import_name": null, "source_any": null, "type_of_any": 6}], "type_ref": "builtins.tuple"}}}}, "_get_formatted_value": {".class": "SymbolTableNode", "kind": "Mdef", "node": {".class": "FuncDef", "arg_kinds": [0], "arg_names": ["self"], "flags": [], "fullname": "abjad.scheme.SchemeColor._get_formatted_value", "name": "_get_formatted_value", "type": null}}}, "tuple_type": null, "type_vars": [], "typeddict_type": null}}, "SchemeMoment": {".class": "SymbolTableNode", "kind": "Gdef", "node": {".class": "TypeInfo", "_promote": null, "abstract_attributes": [], "bases": ["abjad.scheme.Scheme"], "declared_metaclass": null, "defn": {".class": "ClassDef", "fullname": "abjad.scheme.SchemeMoment", "name": "SchemeMoment", "type_vars": []}, "flags": [], "fullname": "abjad.scheme.SchemeMoment", "metaclass_type": null, "metadata": {}, "module_name": "abjad.scheme", "mro": ["abjad.scheme.SchemeMoment", "abjad.scheme.Scheme", "builtins.object"], "names": {".class": "SymbolTable", "__eq__": {".class": "SymbolTableNode", "kind": "Mdef", "node": {".class": "FuncDef", "arg_kinds": [0, 0], "arg_names": ["self", "argument"], "flags": [], "fullname": "abjad.scheme.SchemeMoment.__eq__", "name": "__eq__", "type": {".class": "CallableType", "arg_kinds": [0, 0], "arg_names": [null, null], "arg_types": ["abjad.scheme.SchemeMoment", {".class": "AnyType", "missing_import_name": null, "source_any": null, "type_of_any": 1}], "bound_args": [], "def_extras": {"first_arg": "self"}, "fallback": "builtins.function", "implicit": false, "is_ellipsis_args": false, "name": "__eq__ of SchemeMoment", "ret_type": "builtins.bool", "variables": []}}}, "__hash__": {".class": "SymbolTableNode", "kind": "Mdef", "node": {".class": "FuncDef", "arg_kinds": [0], "arg_names": ["self"], "flags": [], "fullname": "abjad.scheme.SchemeMoment.__hash__", "name": "__hash__", "type": {".class": "CallableType", "arg_kinds": [0], "arg_names": ["self"], "arg_types": ["abjad.scheme.SchemeMoment"], "bound_args": [], "def_extras": {"first_arg": "self"}, "fallback": "builtins.function", "implicit": false, "is_ellipsis_args": false, "name": "__hash__ of SchemeMoment", "ret_type": "builtins.int", "variables": []}}}, "__init__": {".class": "SymbolTableNode", "kind": "Mdef", "node": {".class": "FuncDef", "arg_kinds": [0, 1], "arg_names": ["self", "duration"], "flags": [], "fullname": "abjad.scheme.SchemeMoment.__init__", "name": "__init__", "type": {".class": "CallableType", "arg_kinds": [0, 1], "arg_names": ["self", "duration"], "arg_types": ["abjad.scheme.SchemeMoment", {".class": "TypeAliasType", "args": [], "type_ref": "abjad.typings.IntegerPair"}], "bound_args": [], "def_extras": {"first_arg": "self"}, "fallback": "builtins.function", "implicit": false, "is_ellipsis_args": false, "name": "__init__ of SchemeMoment", "ret_type": {".class": "NoneType"}, "variables": []}}}, "__lt__": {".class": "SymbolTableNode", "kind": "Mdef", "node": {".class": "FuncDef", "arg_kinds": [0, 0], "arg_names": ["self", "argument"], "flags": [], "fullname": "abjad.scheme.SchemeMoment.__lt__", "name": "__lt__", "type": {".class": "CallableType", "arg_kinds": [0, 0], "arg_names": [null, null], "arg_types": ["abjad.scheme.SchemeMoment", {".class": "AnyType", "missing_import_name": null, "source_any": null, "type_of_any": 1}], "bound_args": [], "def_extras": {"first_arg": "self"}, "fallback": "builtins.function", "implicit": false, "is_ellipsis_args": false, "name": "__lt__ of SchemeMoment", "ret_type": "builtins.bool", "variables": []}}}, "__slots__": {".class": "SymbolTableNode", "kind": "Mdef", "node": {".class": "Var", "flags": ["is_initialized_in_class"], "fullname": "abjad.scheme.SchemeMoment.__slots__", "name": "__slots__", "type": {".class": "TupleType", "implicit": false, "items": [], "partial_fallback": {".class": "Instance", "args": [{".class": "AnyType", "missing_import_name": null, "source_any": null, "type_of_any": 6}], "type_ref": "builtins.tuple"}}}}, "_get_format_specification": {".class": "SymbolTableNode", "kind": "Mdef", "node": {".class": "FuncDef", "arg_kinds": [0], "arg_names": ["self"], "flags": [], "fullname": "abjad.scheme.SchemeMoment._get_format_specification", "name": "_get_format_specification", "type": null}}, "_get_formatted_value": {".class": "SymbolTableNode", "kind": "Mdef", "node": {".class": "FuncDef", "arg_kinds": [0], "arg_names": ["self"], "flags": [], "fullname": "abjad.scheme.SchemeMoment._get_formatted_value", "name": "_get_formatted_value", "type": null}}, "duration": {".class": "SymbolTableNode", "kind": "Mdef", "node": {".class": "Decorator", "func": {".class": "FuncDef", "arg_kinds": [0], "arg_names": ["self"], "flags": ["is_property", "is_decorated"], "fullname": "abjad.scheme.SchemeMoment.duration", "name": "duration", "type": {".class": "CallableType", "arg_kinds": [0], "arg_names": ["self"], "arg_types": ["abjad.scheme.SchemeMoment"], "bound_args": [], "def_extras": {"first_arg": "self"}, "fallback": "builtins.function", "implicit": false, "is_ellipsis_args": false, "name": "duration of SchemeMoment", "ret_type": "abjad.mathtools.NonreducedFraction", "variables": []}}, "is_overload": false, "var": {".class": "Var", "flags": ["is_initialized_in_class", "is_property", "is_ready"], "fullname": null, "name": "duration", "type": {".class": "CallableType", "arg_kinds": [0], "arg_names": ["self"], "arg_types": ["abjad.scheme.SchemeMoment"], "bound_args": [], "def_extras": {"first_arg": "self"}, "fallback": "builtins.function", "implicit": false, "is_ellipsis_args": false, "name": "duration of SchemeMoment", "ret_type": "abjad.mathtools.NonreducedFraction", "variables": []}}}}}, "tuple_type": null, "type_vars": [], "typeddict_type": null}}, "SchemePair": {".class": "SymbolTableNode", "kind": "Gdef", "node": {".class": "TypeInfo", "_promote": null, "abstract_attributes": [], "bases": ["abjad.scheme.Scheme"], "declared_metaclass": null, "defn": {".class": "ClassDef", "fullname": "abjad.scheme.SchemePair", "name": "SchemePair", "type_vars": []}, "flags": [], "fullname": "abjad.scheme.SchemePair", "metaclass_type": null, "metadata": {}, "module_name": "abjad.scheme", "mro": ["abjad.scheme.SchemePair", "abjad.scheme.Scheme", "builtins.object"], "names": {".class": "SymbolTable", "__format__": {".class": "SymbolTableNode", "kind": "Mdef", "node": {".class": "FuncDef", "arg_kinds": [0, 1], "arg_names": ["self", "format_specification"], "flags": [], "fullname": "abjad.scheme.SchemePair.__format__", "name": "__format__", "type": {".class": "CallableType", "arg_kinds": [0, 1], "arg_names": ["self", "format_specification"], "arg_types": ["abjad.scheme.SchemePair", {".class": "AnyType", "missing_import_name": null, "source_any": null, "type_of_any": 1}], "bound_args": [], "def_extras": {"first_arg": "self"}, "fallback": "builtins.function", "implicit": false, "is_ellipsis_args": false, "name": "__format__ of SchemePair", "ret_type": "builtins.str", "variables": []}}}, "__init__": {".class": "SymbolTableNode", "kind": "Mdef", "node": {".class": "FuncDef", "arg_kinds": [0, 1], "arg_names": ["self", "value"], "flags": [], "fullname": "abjad.scheme.SchemePair.__init__", "name": "__init__", "type": {".class": "CallableType", "arg_kinds": [0, 1], "arg_names": ["self", "value"], "arg_types": ["abjad.scheme.SchemePair", {".class": "AnyType", "missing_import_name": null, "source_any": null, "type_of_any": 1}], "bound_args": [], "def_extras": {"first_arg": "self"}, "fallback": "builtins.function", "implicit": false, "is_ellipsis_args": false, "name": "__init__ of SchemePair", "ret_type": {".class": "NoneType"}, "variables": []}}}, "__slots__": {".class": "SymbolTableNode", "kind": "Mdef", "node": {".class": "Var", "flags": ["is_initialized_in_class"], "fullname": "abjad.scheme.SchemePair.__slots__", "name": "__slots__", "type": {".class": "TupleType", "implicit": false, "items": ["builtins.str"], "partial_fallback": {".class": "Instance", "args": [{".class": "AnyType", "missing_import_name": null, "source_any": null, "type_of_any": 6}], "type_ref": "builtins.tuple"}}}}, "_get_format_specification": {".class": "SymbolTableNode", "kind": "Mdef", "node": {".class": "FuncDef", "arg_kinds": [0], "arg_names": ["self"], "flags": [], "fullname": "abjad.scheme.SchemePair._get_format_specification", "name": "_get_format_specification", "type": null}}, "_get_formatted_value": {".class": "SymbolTableNode", "kind": "Mdef", "node": {".class": "FuncDef", "arg_kinds": [0], "arg_names": ["self"], "flags": [], "fullname": "abjad.scheme.SchemePair._get_formatted_value", "name": "_get_formatted_value", "type": null}}, "_get_lilypond_format": {".class": "SymbolTableNode", "kind": "Mdef", "node": {".class": "FuncDef", "arg_kinds": [0], "arg_names": ["self"], "flags": [], "fullname": "abjad.scheme.SchemePair._get_lilypond_format", "name": "_get_lilypond_format", "type": null}}, "left": {".class": "SymbolTableNode", "kind": "Mdef", "node": {".class": "Decorator", "func": {".class": "FuncDef", "arg_kinds": [0], "arg_names": ["self"], "flags": ["is_property", "is_decorated"], "fullname": "abjad.scheme.SchemePair.left", "name": "left", "type": {".class": "CallableType", "arg_kinds": [0], "arg_names": ["self"], "arg_types": ["abjad.scheme.SchemePair"], "bound_args": [], "def_extras": {"first_arg": "self"}, "fallback": "builtins.function", "implicit": false, "is_ellipsis_args": false, "name": "left of SchemePair", "ret_type": {".class": "AnyType", "missing_import_name": null, "source_any": null, "type_of_any": 2}, "variables": []}}, "is_overload": false, "var": {".class": "Var", "flags": ["is_initialized_in_class", "is_property", "is_ready"], "fullname": null, "name": "left", "type": {".class": "CallableType", "arg_kinds": [0], "arg_names": ["self"], "arg_types": ["abjad.scheme.SchemePair"], "bound_args": [], "def_extras": {"first_arg": "self"}, "fallback": "builtins.function", "implicit": false, "is_ellipsis_args": false, "name": "left of SchemePair", "ret_type": {".class": "AnyType", "missing_import_name": null, "source_any": null, "type_of_any": 2}, "variables": []}}}}, "right": {".class": "SymbolTableNode", "kind": "Mdef", "node": {".class": "Decorator", "func": {".class": "FuncDef", "arg_kinds": [0], "arg_names": ["self"], "flags": ["is_property", "is_decorated"], "fullname": "abjad.scheme.SchemePair.right", "name": "right", "type": {".class": "CallableType", "arg_kinds": [0], "arg_names": ["self"], "arg_types": ["abjad.scheme.SchemePair"], "bound_args": [], "def_extras": {"first_arg": "self"}, "fallback": "builtins.function", "implicit": false, "is_ellipsis_args": false, "name": "right of SchemePair", "ret_type": {".class": "AnyType", "missing_import_name": null, "source_any": null, "type_of_any": 2}, "variables": []}}, "is_overload": false, "var": {".class": "Var", "flags": ["is_initialized_in_class", "is_property", "is_ready"], "fullname": null, "name": "right", "type": {".class": "CallableType", "arg_kinds": [0], "arg_names": ["self"], "arg_types": ["abjad.scheme.SchemePair"], "bound_args": [], "def_extras": {"first_arg": "self"}, "fallback": "builtins.function", "implicit": false, "is_ellipsis_args": false, "name": "right of SchemePair", "ret_type": {".class": "AnyType", "missing_import_name": null, "source_any": null, "type_of_any": 2}, "variables": []}}}}}, "tuple_type": null, "type_vars": [], "typeddict_type": null}}, "SchemeSymbol": {".class": "SymbolTableNode", "kind": "Gdef", "node": {".class": "TypeInfo", "_promote": null, "abstract_attributes": [], "bases": ["abjad.scheme.Scheme"], "declared_metaclass": null, "defn": {".class": "ClassDef", "fullname": "abjad.scheme.SchemeSymbol", "name": "SchemeSymbol", "type_vars": []}, "flags": [], "fullname": "abjad.scheme.SchemeSymbol", "metaclass_type": null, "metadata": {}, "module_name": "abjad.scheme", "mro": ["abjad.scheme.SchemeSymbol", "abjad.scheme.Scheme", "builtins.object"], "names": {".class": "SymbolTable", "__init__": {".class": "SymbolTableNode", "kind": "Mdef", "node": {".class": "FuncDef", "arg_kinds": [0, 1], "arg_names": ["self", "symbol"], "flags": [], "fullname": "abjad.scheme.SchemeSymbol.__init__", "name": "__init__", "type": {".class": "CallableType", "arg_kinds": [0, 1], "arg_names": ["self", "symbol"], "arg_types": ["abjad.scheme.SchemeSymbol", "builtins.str"], "bound_args": [], "def_extras": {"first_arg": "self"}, "fallback": "builtins.function", "implicit": false, "is_ellipsis_args": false, "name": "__init__ of SchemeSymbol", "ret_type": {".class": "NoneType"}, "variables": []}}}, "__slots__": {".class": "SymbolTableNode", "kind": "Mdef", "node": {".class": "Var", "flags": ["is_initialized_in_class"], "fullname": "abjad.scheme.SchemeSymbol.__slots__", "name": "__slots__", "type": {".class": "TupleType", "implicit": false, "items": [], "partial_fallback": {".class": "Instance", "args": [{".class": "AnyType", "missing_import_name": null, "source_any": null, "type_of_any": 6}], "type_ref": "builtins.tuple"}}}}, "_get_format_specification": {".class": "SymbolTableNode", "kind": "Mdef", "node": {".class": "FuncDef", "arg_kinds": [0], "arg_names": ["self"], "flags": [], "fullname": "abjad.scheme.SchemeSymbol._get_format_specification", "name": "_get_format_specification", "type": null}}, "symbol": {".class": "SymbolTableNode", "kind": "Mdef", "node": {".class": "Decorator", "func": {".class": "FuncDef", "arg_kinds": [0], "arg_names": ["self"], "flags": ["is_property", "is_decorated"], "fullname": "abjad.scheme.SchemeSymbol.symbol", "name": "symbol", "type": {".class": "CallableType", "arg_kinds": [0], "arg_names": ["self"], "arg_types": ["abjad.scheme.SchemeSymbol"], "bound_args": [], "def_extras": {"first_arg": "self"}, "fallback": "builtins.function", "implicit": false, "is_ellipsis_args": false, "name": "symbol of SchemeSymbol", "ret_type": "builtins.str", "variables": []}}, "is_overload": false, "var": {".class": "Var", "flags": ["is_initialized_in_class", "is_property", "is_ready"], "fullname": null, "name": "symbol", "type": {".class": "CallableType", "arg_kinds": [0], "arg_names": ["self"], "arg_types": ["abjad.scheme.SchemeSymbol"], "bound_args": [], "def_extras": {"first_arg": "self"}, "fallback": "builtins.function", "implicit": false, "is_ellipsis_args": false, "name": "symbol of SchemeSymbol", "ret_type": "builtins.str", "variables": []}}}}}, "tuple_type": null, "type_vars": [], "typeddict_type": null}}, "SchemeVector": {".class": "SymbolTableNode", "kind": "Gdef", "node": {".class": "TypeInfo", "_promote": null, "abstract_attributes": [], "bases": ["abjad.scheme.Scheme"], "declared_metaclass": null, "defn": {".class": "ClassDef", "fullname": "abjad.scheme.SchemeVector", "name": "SchemeVector", "type_vars": []}, "flags": [], "fullname": "abjad.scheme.SchemeVector", "metaclass_type": null, "metadata": {}, "module_name": "abjad.scheme", "mro": ["abjad.scheme.SchemeVector", "abjad.scheme.Scheme", "builtins.object"], "names": {".class": "SymbolTable", "__init__": {".class": "SymbolTableNode", "kind": "Mdef", "node": {".class": "FuncDef", "arg_kinds": [0, 1], "arg_names": ["self", "value"], "flags": [], "fullname": "abjad.scheme.SchemeVector.__init__", "name": "__init__", "type": {".class": "CallableType", "arg_kinds": [0, 1], "arg_names": ["self", "value"], "arg_types": ["abjad.scheme.SchemeVector", {".class": "Instance", "args": [{".class": "AnyType", "missing_import_name": null, "source_any": null, "type_of_any": 4}], "type_ref": "builtins.list"}], "bound_args": [], "def_extras": {"first_arg": "self"}, "fallback": "builtins.function", "implicit": false, "is_ellipsis_args": false, "name": "__init__ of SchemeVector", "ret_type": {".class": "NoneType"}, "variables": []}}}, "__slots__": {".class": "SymbolTableNode", "kind": "Mdef", "node": {".class": "Var", "flags": ["is_initialized_in_class"], "fullname": "abjad.scheme.SchemeVector.__slots__", "name": "__slots__", "type": {".class": "TupleType", "implicit": false, "items": [], "partial_fallback": {".class": "Instance", "args": [{".class": "AnyType", "missing_import_name": null, "source_any": null, "type_of_any": 6}], "type_ref": "builtins.tuple"}}}}, "_get_format_specification": {".class": "SymbolTableNode", "kind": "Mdef", "node": {".class": "FuncDef", "arg_kinds": [0], "arg_names": ["self"], "flags": [], "fullname": "abjad.scheme.SchemeVector._get_format_specification", "name": "_get_format_specification", "type": null}}}, "tuple_type": null, "type_vars": [], "typeddict_type": null}}, "SchemeVectorConstant": {".class": "SymbolTableNode", "kind": "Gdef", "node": {".class": "TypeInfo", "_promote": null, "abstract_attributes": [], "bases": ["abjad.scheme.Scheme"], "declared_metaclass": null, "defn": {".class": "ClassDef", "fullname": "abjad.scheme.SchemeVectorConstant", "name": "SchemeVectorConstant", "type_vars": []}, "flags": [], "fullname": "abjad.scheme.SchemeVectorConstant", "metaclass_type": null, "metadata": {}, "module_name": "abjad.scheme", "mro": ["abjad.scheme.SchemeVectorConstant", "abjad.scheme.Scheme", "builtins.object"], "names": {".class": "SymbolTable", "__init__": {".class": "SymbolTableNode", "kind": "Mdef", "node": {".class": "FuncDef", "arg_kinds": [0, 1], "arg_names": ["self", "value"], "flags": [], "fullname": "abjad.scheme.SchemeVectorConstant.__init__", "name": "__init__", "type": {".class": "CallableType", "arg_kinds": [0, 1], "arg_names": ["self", "value"], "arg_types": ["abjad.scheme.SchemeVectorConstant", {".class": "Instance", "args": [{".class": "AnyType", "missing_import_name": null, "source_any": null, "type_of_any": 4}], "type_ref": "builtins.list"}], "bound_args": [], "def_extras": {"first_arg": "self"}, "fallback": "builtins.function", "implicit": false, "is_ellipsis_args": false, "name": "__init__ of SchemeVectorConstant", "ret_type": {".class": "NoneType"}, "variables": []}}}, "__slots__": {".class": "SymbolTableNode", "kind": "Mdef", "node": {".class": "Var", "flags": ["is_initialized_in_class"], "fullname": "abjad.scheme.SchemeVectorConstant.__slots__", "name": "__slots__", "type": {".class": "TupleType", "implicit": false, "items": [], "partial_fallback": {".class": "Instance", "args": [{".class": "AnyType", "missing_import_name": null, "source_any": null, "type_of_any": 6}], "type_ref": "builtins.tuple"}}}}, "_get_format_specification": {".class": "SymbolTableNode", "kind": "Mdef", "node": {".class": "FuncDef", "arg_kinds": [0], "arg_names": ["self"], "flags": [], "fullname": "abjad.scheme.SchemeVectorConstant._get_format_specification", "name": "_get_format_specification", "type": null}}}, "tuple_type": null, "type_vars": [], "typeddict_type": null}}, "SpacingVector": {".class": "SymbolTableNode", "kind": "Gdef", "node": {".class": "TypeInfo", "_promote": null, "abstract_attributes": [], "bases": ["abjad.scheme.SchemeVector"], "declared_metaclass": null, "defn": {".class": "ClassDef", "fullname": "abjad.scheme.SpacingVector", "name": "SpacingVector", "type_vars": []}, "flags": [], "fullname": "abjad.scheme.SpacingVector", "metaclass_type": null, "metadata": {}, "module_name": "abjad.scheme", "mro": ["abjad.scheme.SpacingVector", "abjad.scheme.SchemeVector", "abjad.scheme.Scheme", "builtins.object"], "names": {".class": "SymbolTable", "__init__": {".class": "SymbolTableNode", "kind": "Mdef", "node": {".class": "FuncDef", "arg_kinds": [0, 1, 1, 1, 1], "arg_names": ["self", "basic_distance", "minimum_distance", "padding", "stretchability"], "flags": [], "fullname": "abjad.scheme.SpacingVector.__init__", "name": "__init__", "type": {".class": "CallableType", "arg_kinds": [0, 1, 1, 1, 1], "arg_names": ["self", "basic_distance", "minimum_distance", "padding", "stretchability"], "arg_types": ["abjad.scheme.SpacingVector", {".class": "TypeAliasType", "args": [], "type_ref": "abjad.typings.Number"}, {".class": "TypeAliasType", "args": [], "type_ref": "abjad.typings.Number"}, {".class": "TypeAliasType", "args": [], "type_ref": "abjad.typings.Number"}, {".class": "TypeAliasType", "args": [], "type_ref": "abjad.typings.Number"}], "bound_args": [], "def_extras": {"first_arg": "self"}, "fallback": "builtins.function", "implicit": false, "is_ellipsis_args": false, "name": "__init__ of SpacingVector", "ret_type": {".class": "NoneType"}, "variables": []}}}, "__slots__": {".class": "SymbolTableNode", "kind": "Mdef", "node": {".class": "Var", "flags": ["is_initialized_in_class"], "fullname": "abjad.scheme.SpacingVector.__slots__", "name": "__slots__", "type": {".class": "TupleType", "implicit": false, "items": [], "partial_fallback": {".class": "Instance", "args": [{".class": "AnyType", "missing_import_name": null, "source_any": null, "type_of_any": 6}], "type_ref": "builtins.tuple"}}}}}, "tuple_type": null, "type_vars": [], "typeddict_type": null}}, "StorageFormatManager": {".class": "SymbolTableNode", "cross_ref": "abjad.system.StorageFormatManager.StorageFormatManager", "kind": "Gdef"}, "String": {".class": "SymbolTableNode", "cross_ref": "abjad.utilities.String.String", "kind": "Gdef"}, "__doc__": {".class": "SymbolTableNode", "kind": "Gdef", "node": {".class": "Var", "flags": ["is_ready"], "fullname": "abjad.scheme.__doc__", "name": "__doc__", "type": "builtins.str"}}, "__file__": {".class": "SymbolTableNode", "kind": "Gdef", "node": {".class": "Var", "flags": ["is_ready"], "fullname": "abjad.scheme.__file__", "name": "__file__", "type": "builtins.str"}}, "__name__": {".class": "SymbolTableNode", "kind": "Gdef", "node": {".class": "Var", "flags": ["is_ready"], "fullname": "abjad.scheme.__name__", "name": "__name__", "type": "builtins.str"}}, "__package__": {".class": "SymbolTableNode", "kind": "Gdef", "node": {".class": "Var", "flags": ["is_ready"], "fullname": "abjad.scheme.__package__", "name": "__package__", "type": "builtins.str"}}, "enums": {".class": "SymbolTableNode", "cross_ref": "abjad.enums", "kind": "Gdef"}, "functools": {".class": "SymbolTableNode", "cross_ref": "functools", "kind": "Gdef"}, "typing": {".class": "SymbolTableNode", "cross_ref": "typing", "kind": "Gdef"}, "typings": {".class": "SymbolTableNode", "cross_ref": "abjad.typings", "kind": "Gdef"}}, "path": "/Users/evansdsg2/abjad/abjad/scheme.py"}