{".class": "MypyFile", "_fullname": "abjad.top.sequence", "is_partial_stub_package": false, "is_stub": false, "names": {".class": "SymbolTable", "__doc__": {".class": "SymbolTableNode", "kind": "Gdef", "node": {".class": "Var", "flags": ["is_ready"], "fullname": "abjad.top.sequence.__doc__", "name": "__doc__", "type": "builtins.str"}}, "__file__": {".class": "SymbolTableNode", "kind": "Gdef", "node": {".class": "Var", "flags": ["is_ready"], "fullname": "abjad.top.sequence.__file__", "name": "__file__", "type": "builtins.str"}}, "__name__": {".class": "SymbolTableNode", "kind": "Gdef", "node": {".class": "Var", "flags": ["is_ready"], "fullname": "abjad.top.sequence.__name__", "name": "__name__", "type": "builtins.str"}}, "__package__": {".class": "SymbolTableNode", "kind": "Gdef", "node": {".class": "Var", "flags": ["is_ready"], "fullname": "abjad.top.sequence.__package__", "name": "__package__", "type": "builtins.str"}}, "sequence": {".class": "SymbolTableNode", "kind": "Gdef", "node": {".class": "FuncDef", "arg_kinds": [1, 4], "arg_names": ["items", "keywords"], "flags": [], "fullname": "abjad.top.sequence.sequence", "name": "sequence", "type": null}}}, "path": "/Users/evansdsg2/abjad/abjad/top/sequence.py"}