{".class": "MypyFile", "_fullname": "abjad.system.FilesystemState", "is_partial_stub_package": false, "is_stub": false, "names": {".class": "SymbolTable", "ContextManager": {".class": "SymbolTableNode", "cross_ref": "abjad.system.ContextManager.ContextManager", "kind": "Gdef"}, "FilesystemState": {".class": "SymbolTableNode", "kind": "Gdef", "node": {".class": "TypeInfo", "_promote": null, "abstract_attributes": [], "bases": ["abjad.system.ContextManager.ContextManager"], "declared_metaclass": null, "defn": {".class": "ClassDef", "fullname": "abjad.system.FilesystemState.FilesystemState", "name": "FilesystemState", "type_vars": []}, "flags": [], "fullname": "abjad.system.FilesystemState.FilesystemState", "metaclass_type": null, "metadata": {}, "module_name": "abjad.system.FilesystemState", "mro": ["abjad.system.FilesystemState.FilesystemState", "abjad.system.ContextManager.ContextManager", "builtins.object"], "names": {".class": "SymbolTable", "__documentation_section__": {".class": "SymbolTableNode", "kind": "Mdef", "node": {".class": "Var", "flags": ["is_initialized_in_class", "is_ready"], "fullname": "abjad.system.FilesystemState.FilesystemState.__documentation_section__", "name": "__documentation_section__", "type": "builtins.str"}}, "__enter__": {".class": "SymbolTableNode", "kind": "Mdef", "node": {".class": "FuncDef", "arg_kinds": [0], "arg_names": ["self"], "flags": [], "fullname": "abjad.system.FilesystemState.FilesystemState.__enter__", "name": "__enter__", "type": null}}, "__exit__": {".class": "SymbolTableNode", "kind": "Mdef", "node": {".class": "FuncDef", "arg_kinds": [0, 0, 0, 0], "arg_names": ["self", "exg_type", "exc_value", "trackeback"], "flags": [], "fullname": "abjad.system.FilesystemState.FilesystemState.__exit__", "name": "__exit__", "type": null}}, "__init__": {".class": "SymbolTableNode", "kind": "Mdef", "node": {".class": "FuncDef", "arg_kinds": [0, 1, 1], "arg_names": ["self", "keep", "remove"], "flags": [], "fullname": "abjad.system.FilesystemState.FilesystemState.__init__", "name": "__init__", "type": null}}, "__slots__": {".class": "SymbolTableNode", "kind": "Mdef", "node": {".class": "Var", "flags": ["is_initialized_in_class"], "fullname": "abjad.system.FilesystemState.FilesystemState.__slots__", "name": "__slots__", "type": {".class": "TupleType", "implicit": false, "items": ["builtins.str", "builtins.str"], "partial_fallback": {".class": "Instance", "args": [{".class": "AnyType", "missing_import_name": null, "source_any": null, "type_of_any": 6}], "type_ref": "builtins.tuple"}}}}, "_keep": {".class": "SymbolTableNode", "implicit": true, "kind": "Mdef", "node": {".class": "Var", "flags": [], "fullname": "abjad.system.FilesystemState.FilesystemState._keep", "name": "_keep", "type": {".class": "AnyType", "missing_import_name": null, "source_any": null, "type_of_any": 1}}}, "_remove": {".class": "SymbolTableNode", "implicit": true, "kind": "Mdef", "node": {".class": "Var", "flags": [], "fullname": "abjad.system.FilesystemState.FilesystemState._remove", "name": "_remove", "type": {".class": "AnyType", "missing_import_name": null, "source_any": null, "type_of_any": 1}}}, "keep": {".class": "SymbolTableNode", "kind": "Mdef", "node": {".class": "Decorator", "func": {".class": "FuncDef", "arg_kinds": [0], "arg_names": ["self"], "flags": ["is_property", "is_decorated"], "fullname": "abjad.system.FilesystemState.FilesystemState.keep", "name": "keep", "type": null}, "is_overload": false, "var": {".class": "Var", "flags": ["is_initialized_in_class", "is_property", "is_ready"], "fullname": null, "name": "keep", "type": {".class": "CallableType", "arg_kinds": [0], "arg_names": ["self"], "arg_types": ["abjad.system.FilesystemState.FilesystemState"], "bound_args": [], "def_extras": {}, "fallback": "builtins.function", "implicit": true, "is_ellipsis_args": false, "name": "keep of FilesystemState", "ret_type": {".class": "AnyType", "missing_import_name": null, "source_any": null, "type_of_any": 1}, "variables": []}}}}, "remove": {".class": "SymbolTableNode", "kind": "Mdef", "node": {".class": "Decorator", "func": {".class": "FuncDef", "arg_kinds": [0], "arg_names": ["self"], "flags": ["is_property", "is_decorated"], "fullname": "abjad.system.FilesystemState.FilesystemState.remove", "name": "remove", "type": null}, "is_overload": false, "var": {".class": "Var", "flags": ["is_initialized_in_class", "is_property", "is_ready"], "fullname": null, "name": "remove", "type": {".class": "CallableType", "arg_kinds": [0], "arg_names": ["self"], "arg_types": ["abjad.system.FilesystemState.FilesystemState"], "bound_args": [], "def_extras": {}, "fallback": "builtins.function", "implicit": true, "is_ellipsis_args": false, "name": "remove of FilesystemState", "ret_type": {".class": "AnyType", "missing_import_name": null, "source_any": null, "type_of_any": 1}, "variables": []}}}}}, "tuple_type": null, "type_vars": [], "typeddict_type": null}}, "__doc__": {".class": "SymbolTableNode", "kind": "Gdef", "node": {".class": "Var", "flags": ["is_ready"], "fullname": "abjad.system.FilesystemState.__doc__", "name": "__doc__", "type": "builtins.str"}}, "__file__": {".class": "SymbolTableNode", "kind": "Gdef", "node": {".class": "Var", "flags": ["is_ready"], "fullname": "abjad.system.FilesystemState.__file__", "name": "__file__", "type": "builtins.str"}}, "__name__": {".class": "SymbolTableNode", "kind": "Gdef", "node": {".class": "Var", "flags": ["is_ready"], "fullname": "abjad.system.FilesystemState.__name__", "name": "__name__", "type": "builtins.str"}}, "__package__": {".class": "SymbolTableNode", "kind": "Gdef", "node": {".class": "Var", "flags": ["is_ready"], "fullname": "abjad.system.FilesystemState.__package__", "name": "__package__", "type": "builtins.str"}}, "collections": {".class": "SymbolTableNode", "cross_ref": "collections", "kind": "Gdef"}, "filecmp": {".class": "SymbolTableNode", "cross_ref": "filecmp", "kind": "Gdef"}, "os": {".class": "SymbolTableNode", "cross_ref": "os", "kind": "Gdef"}, "shutil": {".class": "SymbolTableNode", "cross_ref": "shutil", "kind": "Gdef"}}, "path": "/Users/evansdsg2/abjad/abjad/system/FilesystemState.py"}