{".class": "MypyFile", "_fullname": "abjad.system.TemporaryDirectory", "is_partial_stub_package": false, "is_stub": false, "names": {".class": "SymbolTable", "ContextManager": {".class": "SymbolTableNode", "cross_ref": "abjad.system.ContextManager.ContextManager", "kind": "Gdef"}, "TemporaryDirectory": {".class": "SymbolTableNode", "kind": "Gdef", "node": {".class": "TypeInfo", "_promote": null, "abstract_attributes": [], "bases": ["abjad.system.ContextManager.ContextManager"], "declared_metaclass": null, "defn": {".class": "ClassDef", "fullname": "abjad.system.TemporaryDirectory.TemporaryDirectory", "name": "TemporaryDirectory", "type_vars": []}, "flags": [], "fullname": "abjad.system.TemporaryDirectory.TemporaryDirectory", "metaclass_type": null, "metadata": {}, "module_name": "abjad.system.TemporaryDirectory", "mro": ["abjad.system.TemporaryDirectory.TemporaryDirectory", "abjad.system.ContextManager.ContextManager", "builtins.object"], "names": {".class": "SymbolTable", "__documentation_section__": {".class": "SymbolTableNode", "kind": "Mdef", "node": {".class": "Var", "flags": ["is_initialized_in_class", "is_ready"], "fullname": "abjad.system.TemporaryDirectory.TemporaryDirectory.__documentation_section__", "name": "__documentation_section__", "type": "builtins.str"}}, "__enter__": {".class": "SymbolTableNode", "kind": "Mdef", "node": {".class": "FuncDef", "arg_kinds": [0], "arg_names": ["self"], "flags": [], "fullname": "abjad.system.TemporaryDirectory.TemporaryDirectory.__enter__", "name": "__enter__", "type": null}}, "__exit__": {".class": "SymbolTableNode", "kind": "Mdef", "node": {".class": "FuncDef", "arg_kinds": [0, 0, 0, 0], "arg_names": ["self", "exc_type", "exc_value", "traceback"], "flags": [], "fullname": "abjad.system.TemporaryDirectory.TemporaryDirectory.__exit__", "name": "__exit__", "type": null}}, "__init__": {".class": "SymbolTableNode", "kind": "Mdef", "node": {".class": "FuncDef", "arg_kinds": [0, 1], "arg_names": ["self", "parent_directory"], "flags": [], "fullname": "abjad.system.TemporaryDirectory.TemporaryDirectory.__init__", "name": "__init__", "type": null}}, "__slots__": {".class": "SymbolTableNode", "kind": "Mdef", "node": {".class": "Var", "flags": ["is_initialized_in_class"], "fullname": "abjad.system.TemporaryDirectory.TemporaryDirectory.__slots__", "name": "__slots__", "type": {".class": "TupleType", "implicit": false, "items": ["builtins.str", "builtins.str"], "partial_fallback": {".class": "Instance", "args": [{".class": "AnyType", "missing_import_name": null, "source_any": null, "type_of_any": 6}], "type_ref": "builtins.tuple"}}}}, "_parent_directory": {".class": "SymbolTableNode", "implicit": true, "kind": "Mdef", "node": {".class": "Var", "flags": [], "fullname": "abjad.system.TemporaryDirectory.TemporaryDirectory._parent_directory", "name": "_parent_directory", "type": {".class": "AnyType", "missing_import_name": null, "source_any": null, "type_of_any": 1}}}, "_temporary_directory": {".class": "SymbolTableNode", "implicit": true, "kind": "Mdef", "node": {".class": "Var", "flags": [], "fullname": "abjad.system.TemporaryDirectory.TemporaryDirectory._temporary_directory", "name": "_temporary_directory", "type": {".class": "AnyType", "missing_import_name": null, "source_any": null, "type_of_any": 1}}}, "parent_directory": {".class": "SymbolTableNode", "kind": "Mdef", "node": {".class": "Decorator", "func": {".class": "FuncDef", "arg_kinds": [0], "arg_names": ["self"], "flags": ["is_property", "is_decorated"], "fullname": "abjad.system.TemporaryDirectory.TemporaryDirectory.parent_directory", "name": "parent_directory", "type": null}, "is_overload": false, "var": {".class": "Var", "flags": ["is_initialized_in_class", "is_property", "is_ready"], "fullname": null, "name": "parent_directory", "type": {".class": "CallableType", "arg_kinds": [0], "arg_names": ["self"], "arg_types": ["abjad.system.TemporaryDirectory.TemporaryDirectory"], "bound_args": [], "def_extras": {}, "fallback": "builtins.function", "implicit": true, "is_ellipsis_args": false, "name": "parent_directory of TemporaryDirectory", "ret_type": {".class": "AnyType", "missing_import_name": null, "source_any": null, "type_of_any": 1}, "variables": []}}}}, "temporary_directory": {".class": "SymbolTableNode", "kind": "Mdef", "node": {".class": "Decorator", "func": {".class": "FuncDef", "arg_kinds": [0], "arg_names": ["self"], "flags": ["is_property", "is_decorated"], "fullname": "abjad.system.TemporaryDirectory.TemporaryDirectory.temporary_directory", "name": "temporary_directory", "type": null}, "is_overload": false, "var": {".class": "Var", "flags": ["is_initialized_in_class", "is_property", "is_ready"], "fullname": null, "name": "temporary_directory", "type": {".class": "CallableType", "arg_kinds": [0], "arg_names": ["self"], "arg_types": ["abjad.system.TemporaryDirectory.TemporaryDirectory"], "bound_args": [], "def_extras": {}, "fallback": "builtins.function", "implicit": true, "is_ellipsis_args": false, "name": "temporary_directory of TemporaryDirectory", "ret_type": {".class": "AnyType", "missing_import_name": null, "source_any": null, "type_of_any": 1}, "variables": []}}}}}, "tuple_type": null, "type_vars": [], "typeddict_type": null}}, "__doc__": {".class": "SymbolTableNode", "kind": "Gdef", "node": {".class": "Var", "flags": ["is_ready"], "fullname": "abjad.system.TemporaryDirectory.__doc__", "name": "__doc__", "type": "builtins.str"}}, "__file__": {".class": "SymbolTableNode", "kind": "Gdef", "node": {".class": "Var", "flags": ["is_ready"], "fullname": "abjad.system.TemporaryDirectory.__file__", "name": "__file__", "type": "builtins.str"}}, "__name__": {".class": "SymbolTableNode", "kind": "Gdef", "node": {".class": "Var", "flags": ["is_ready"], "fullname": "abjad.system.TemporaryDirectory.__name__", "name": "__name__", "type": "builtins.str"}}, "__package__": {".class": "SymbolTableNode", "kind": "Gdef", "node": {".class": "Var", "flags": ["is_ready"], "fullname": "abjad.system.TemporaryDirectory.__package__", "name": "__package__", "type": "builtins.str"}}, "shutil": {".class": "SymbolTableNode", "cross_ref": "shutil", "kind": "Gdef"}, "tempfile": {".class": "SymbolTableNode", "cross_ref": "tempfile", "kind": "Gdef"}}, "path": "/Users/evansdsg2/abjad/abjad/system/TemporaryDirectory.py"}