{".class": "MypyFile", "_fullname": "abjadext.tonality.ChordQuality", "is_partial_stub_package": false, "is_stub": false, "names": {".class": "SymbolTable", "ChordQuality": {".class": "SymbolTableNode", "kind": "Gdef", "node": {".class": "TypeInfo", "_promote": null, "abstract_attributes": [], "bases": ["builtins.object"], "declared_metaclass": null, "defn": {".class": "ClassDef", "fullname": "abjadext.tonality.ChordQuality.ChordQuality", "name": "ChordQuality", "type_vars": []}, "flags": [], "fullname": "abjadext.tonality.ChordQuality.ChordQuality", "metaclass_type": null, "metadata": {}, "module_name": "abjadext.tonality.ChordQuality", "mro": ["abjadext.tonality.ChordQuality.ChordQuality", "builtins.object"], "names": {".class": "SymbolTable", "__eq__": {".class": "SymbolTableNode", "kind": "Mdef", "node": {".class": "FuncDef", "arg_kinds": [0, 0], "arg_names": ["self", "argument"], "flags": [], "fullname": "abjadext.tonality.ChordQuality.ChordQuality.__eq__", "name": "__eq__", "type": null}}, "__hash__": {".class": "SymbolTableNode", "kind": "Mdef", "node": {".class": "FuncDef", "arg_kinds": [0], "arg_names": ["self"], "flags": [], "fullname": "abjadext.tonality.ChordQuality.ChordQuality.__hash__", "name": "__hash__", "type": null}}, "__init__": {".class": "SymbolTableNode", "kind": "Mdef", "node": {".class": "FuncDef", "arg_kinds": [0, 1], "arg_names": ["self", "quality_string"], "flags": [], "fullname": "abjadext.tonality.ChordQuality.ChordQuality.__init__", "name": "__init__", "type": null}}, "__repr__": {".class": "SymbolTableNode", "kind": "Mdef", "node": {".class": "FuncDef", "arg_kinds": [0], "arg_names": ["self"], "flags": [], "fullname": "abjadext.tonality.ChordQuality.ChordQuality.__repr__", "name": "__repr__", "type": {".class": "CallableType", "arg_kinds": [0], "arg_names": [null], "arg_types": ["abjadext.tonality.ChordQuality.ChordQuality"], "bound_args": [], "def_extras": {"first_arg": "self"}, "fallback": "builtins.function", "implicit": false, "is_ellipsis_args": false, "name": "__repr__ of ChordQuality", "ret_type": "builtins.str", "variables": []}}}, "__slots__": {".class": "SymbolTableNode", "kind": "Mdef", "node": {".class": "Var", "flags": ["is_initialized_in_class"], "fullname": "abjadext.tonality.ChordQuality.ChordQuality.__slots__", "name": "__slots__", "type": {".class": "TupleType", "implicit": false, "items": ["builtins.str"], "partial_fallback": {".class": "Instance", "args": [{".class": "AnyType", "missing_import_name": null, "source_any": null, "type_of_any": 6}], "type_ref": "builtins.tuple"}}}}, "__str__": {".class": "SymbolTableNode", "kind": "Mdef", "node": {".class": "FuncDef", "arg_kinds": [0], "arg_names": ["self"], "flags": [], "fullname": "abjadext.tonality.ChordQuality.ChordQuality.__str__", "name": "__str__", "type": null}}, "_acceptable_quality_strings": {".class": "SymbolTableNode", "kind": "Mdef", "node": {".class": "Var", "flags": ["is_initialized_in_class"], "fullname": "abjadext.tonality.ChordQuality.ChordQuality._acceptable_quality_strings", "name": "_acceptable_quality_strings", "type": {".class": "TupleType", "implicit": false, "items": ["builtins.str", "builtins.str", "builtins.str", "builtins.str", "builtins.str", "builtins.str"], "partial_fallback": {".class": "Instance", "args": [{".class": "AnyType", "missing_import_name": null, "source_any": null, "type_of_any": 6}], "type_ref": "builtins.tuple"}}}}, "_get_format_specification": {".class": "SymbolTableNode", "kind": "Mdef", "node": {".class": "FuncDef", "arg_kinds": [0], "arg_names": ["self"], "flags": [], "fullname": "abjadext.tonality.ChordQuality.ChordQuality._get_format_specification", "name": "_get_format_specification", "type": null}}, "_quality_string": {".class": "SymbolTableNode", "implicit": true, "kind": "Mdef", "node": {".class": "Var", "flags": [], "fullname": "abjadext.tonality.ChordQuality.ChordQuality._quality_string", "name": "_quality_string", "type": {".class": "AnyType", "missing_import_name": null, "source_any": null, "type_of_any": 1}}}, "_uppercase_quality_strings": {".class": "SymbolTableNode", "kind": "Mdef", "node": {".class": "Var", "flags": ["is_initialized_in_class"], "fullname": "abjadext.tonality.ChordQuality.ChordQuality._uppercase_quality_strings", "name": "_uppercase_quality_strings", "type": {".class": "TupleType", "implicit": false, "items": ["builtins.str", "builtins.str", "builtins.str"], "partial_fallback": {".class": "Instance", "args": [{".class": "AnyType", "missing_import_name": null, "source_any": null, "type_of_any": 6}], "type_ref": "builtins.tuple"}}}}, "is_uppercase": {".class": "SymbolTableNode", "kind": "Mdef", "node": {".class": "Decorator", "func": {".class": "FuncDef", "arg_kinds": [0], "arg_names": ["self"], "flags": ["is_property", "is_decorated"], "fullname": "abjadext.tonality.ChordQuality.ChordQuality.is_uppercase", "name": "is_uppercase", "type": null}, "is_overload": false, "var": {".class": "Var", "flags": ["is_initialized_in_class", "is_property", "is_ready"], "fullname": null, "name": "is_uppercase", "type": {".class": "CallableType", "arg_kinds": [0], "arg_names": ["self"], "arg_types": ["abjadext.tonality.ChordQuality.ChordQuality"], "bound_args": [], "def_extras": {}, "fallback": "builtins.function", "implicit": true, "is_ellipsis_args": false, "name": "is_uppercase of ChordQuality", "ret_type": {".class": "AnyType", "missing_import_name": null, "source_any": null, "type_of_any": 1}, "variables": []}}}}, "quality_string": {".class": "SymbolTableNode", "kind": "Mdef", "node": {".class": "Decorator", "func": {".class": "FuncDef", "arg_kinds": [0], "arg_names": ["self"], "flags": ["is_property", "is_decorated"], "fullname": "abjadext.tonality.ChordQuality.ChordQuality.quality_string", "name": "quality_string", "type": null}, "is_overload": false, "var": {".class": "Var", "flags": ["is_initialized_in_class", "is_property", "is_ready"], "fullname": null, "name": "quality_string", "type": {".class": "CallableType", "arg_kinds": [0], "arg_names": ["self"], "arg_types": ["abjadext.tonality.ChordQuality.ChordQuality"], "bound_args": [], "def_extras": {}, "fallback": "builtins.function", "implicit": true, "is_ellipsis_args": false, "name": "quality_string of ChordQuality", "ret_type": {".class": "AnyType", "missing_import_name": null, "source_any": null, "type_of_any": 1}, "variables": []}}}}}, "tuple_type": null, "type_vars": [], "typeddict_type": null}}, "__doc__": {".class": "SymbolTableNode", "kind": "Gdef", "node": {".class": "Var", "flags": ["is_ready"], "fullname": "abjadext.tonality.ChordQuality.__doc__", "name": "__doc__", "type": "builtins.str"}}, "__file__": {".class": "SymbolTableNode", "kind": "Gdef", "node": {".class": "Var", "flags": ["is_ready"], "fullname": "abjadext.tonality.ChordQuality.__file__", "name": "__file__", "type": "builtins.str"}}, "__name__": {".class": "SymbolTableNode", "kind": "Gdef", "node": {".class": "Var", "flags": ["is_ready"], "fullname": "abjadext.tonality.ChordQuality.__name__", "name": "__name__", "type": "builtins.str"}}, "__package__": {".class": "SymbolTableNode", "kind": "Gdef", "node": {".class": "Var", "flags": ["is_ready"], "fullname": "abjadext.tonality.ChordQuality.__package__", "name": "__package__", "type": "builtins.str"}}, "abjad": {".class": "SymbolTableNode", "cross_ref": "abjad", "kind": "Gdef"}}, "path": "/Users/evansdsg2/abjad-ext-tonality/abjadext/tonality/ChordQuality.py"}